Workbook

Sheet Dashboard
A1: Trading Performance Dashboard
A2: Account 91404 (THM00601) • Market FUT, Reg • Currency PKR • Generated 16-Oct-2026 11:35
A4: Latest Trading Day: | B4: =MAX('Daily Summary'!$A$5:$A$404) -> 46311
A6: LATEST TRADING DAY | D6: PERFORMANCE SNAPSHOT
A7: Buy Value | B7: ='Daily Summary'!E40 -> 4845060 | D7: Period | E7: Net P&L (PKR) | F7: Return on Buy
A8: Sell Value | B8: ='Daily Summary'!F40 -> 4855610 | D8: MTD (Oct 2026) | E8: ='MTD Summary'!$B$19 -> 39790.636 | F8: ='MTD Summary'!$B$20 -> 0.00035470732
A9: Gross P&L | B9: ='Daily Summary'!G40 -> 10550 | D9: QTD (Q4 2026) | E9: ='QTD Summary'!$B$19 -> 39790.636 | F9: ='QTD Summary'!$B$20 -> 0.00035470732
A10: Commission | B10: ='Daily Summary'!H40 -> 1578.0732 | D10: YTD (2026) | E10: ='YTD Summary'!$B$19 -> 193263.61 | F10: ='YTD Summary'!$B$20 -> 0.00047928714
A11: SST (13%) | B11: ='Daily Summary'!I40 -> 205.14952
A12: Net P&L | B12: ='Daily Summary'!K40 -> 8766.7772 | D12: ACTIVITY — ALL IMPORTED DATA
A13: Return on Buy | B13: ='Daily Summary'!L40 -> 0.0018094259 | D13: Total Traded Volume (PKR) | E13: ='Daily Summary'!$E$41+'Daily Summary'!$F$41 -> 8.0680211e+08
D14: Executions | E14: 2742
D15: Symbols | E15: =COUNTA('Symbol Performance'!$A$5:$A$61) -> 57
D16: Trading Days | E16: =COUNT('Daily Summary'!$A$5:$A$404) -> 36
D18: BEST / WORST SYMBOL (Net P&L, all dates)
D19: Best Symbol | E19: =INDEX('Symbol Performance'!$A$5:$A$61,MATCH(MAX('Symbol Performance'!$I$5:$I$61),'Symbol Performance'!$I$5:$I$61,0)) -> PRL-AUG | F19: =MAX('Symbol Performance'!$I$5:$I$61) -> 37651.077
D20: Worst Symbol | E20: =INDEX('Symbol Performance'!$A$5:$A$61,MATCH(MIN('Symbol Performance'!$I$5:$I$61),'Symbol Performance'!$I$5:$I$61,0)) -> OGDC-OCTB | F20: =MIN('Symbol Performance'!$I$5:$I$61) -> -3184.0584
A22: • Methodology: Gross P&L = Sell Value − Buy Value (intraday buy/sell flow; Short Sell counts as SELL).
A23: • Commission is sell-side only: sell rate < 54 → 0.0175 paisa/share; ≥ 54 → 0.0325% of sell value. SST = 13% of commission.
A24: • Net P&L = Gross P&L − Commission − SST. Return on Buy = Net P&L ÷ Buy Value (recomputed from totals, never averaged).
A25: • Position status through 16-Oct-2026: all symbols flat (net quantity 0) on every trading day.
A26: • This is a flow-based summary, not FIFO/average-cost realized-position accounting. See the Settings sheet.

Sheet Daily Summary
A1: Daily Summary
A2: One row per trading date — linked live to the Daily Trade Summary blocks.
A4: Date | B4: Buy Qty | C4: Sell Qty | D4: Net Qty | E4: Buy Value (PKR) | F4: Sell Value (PKR) | G4: Gross P&L (PKR) | H4: Commission (PKR) | I4: SST (PKR) | J4: Total Charges (PKR) | K4: Net P&L (PKR) | L4: Return on Buy
A5: 46251 | B5: ='Daily Trade Summary'!B21 -> 70500 | C5: ='Daily Trade Summary'!E21 -> 70500 | D5: ='Daily Trade Summary'!I21 -> 0 | E5: ='Daily Trade Summary'!C21 -> 18267720 | F5: ='Daily Trade Summary'!F21 -> 18287930 | G5: ='Daily Trade Summary'!J21 -> 20210 | H5: ='Daily Trade Summary'!L21 -> 5943.5773 | I5: ='Daily Trade Summary'!M21 -> 772.66504 | J5: ='Daily Trade Summary'!N21 -> 6716.2423 | K5: ='Daily Trade Summary'!O21 -> 13493.758 | L5: =IF($E5=0,"",$K5/$E5) -> 0.00073866677
A6: 46252 | B6: ='Daily Trade Summary'!B47 -> 125640 | C6: ='Daily Trade Summary'!E47 -> 125640 | D6: ='Daily Trade Summary'!I47 -> 0 | E6: ='Daily Trade Summary'!C47 -> 21984905 | F6: ='Daily Trade Summary'!F47 -> 22001335 | G6: ='Daily Trade Summary'!J47 -> 16430 | H6: ='Daily Trade Summary'!L47 -> 6920.3714 | I6: ='Daily Trade Summary'!M47 -> 899.64828 | J6: ='Daily Trade Summary'!N47 -> 7820.0197 | K6: ='Daily Trade Summary'!O47 -> 8609.9803 | L6: =IF($E6=0,"",$K6/$E6) -> 0.00039163146
A7: 46253 | B7: ='Daily Trade Summary'!B70 -> 96000 | C7: ='Daily Trade Summary'!E70 -> 96000 | D7: ='Daily Trade Summary'!I70 -> 0 | E7: ='Daily Trade Summary'!C70 -> 12039745 | F7: ='Daily Trade Summary'!F70 -> 12062720 | G7: ='Daily Trade Summary'!J70 -> 22975 | H7: ='Daily Trade Summary'!L70 -> 3851.2528 | I7: ='Daily Trade Summary'!M70 -> 500.66286 | J7: ='Daily Trade Summary'!N70 -> 4351.9156 | K7: ='Daily Trade Summary'!O70 -> 18623.084 | L7: =IF($E7=0,"",$K7/$E7) -> 0.0015468006
A8: 46254 | B8: ='Daily Trade Summary'!B94 -> 63500 | C8: ='Daily Trade Summary'!E94 -> 63500 | D8: ='Daily Trade Summary'!I94 -> 0 | E8: ='Daily Trade Summary'!C94 -> 10062968 | F8: ='Daily Trade Summary'!F94 -> 10084865 | G8: ='Daily Trade Summary'!J94 -> 21896.51 | H8: ='Daily Trade Summary'!L94 -> 3277.581 | I8: ='Daily Trade Summary'!M94 -> 426.08553 | J8: ='Daily Trade Summary'!N94 -> 3703.6665 | K8: ='Daily Trade Summary'!O94 -> 18192.844 | L8: =IF($E8=0,"",$K8/$E8) -> 0.0018079004
A9: 46255 | B9: ='Daily Trade Summary'!B117 -> 45357 | C9: ='Daily Trade Summary'!E117 -> 45357 | D9: ='Daily Trade Summary'!I117 -> 0 | E9: ='Daily Trade Summary'!C117 -> 8763520 | F9: ='Daily Trade Summary'!F117 -> 8772484.3 | G9: ='Daily Trade Summary'!J117 -> 8964.29 | H9: ='Daily Trade Summary'!L117 -> 2851.0574 | I9: ='Daily Trade Summary'!M117 -> 370.63746 | J9: ='Daily Trade Summary'!N117 -> 3221.6948 | K9: ='Daily Trade Summary'!O117 -> 5742.5952 | L9: =IF($E9=0,"",$K9/$E9) -> 0.00065528408
A10: 46258 | B10: ='Daily Trade Summary'!B140 -> 84004 | C10: ='Daily Trade Summary'!E140 -> 84004 | D10: ='Daily Trade Summary'!I140 -> 0 | E10: ='Daily Trade Summary'!C140 -> 13130113 | F10: ='Daily Trade Summary'!F140 -> 13155567 | G10: ='Daily Trade Summary'!J140 -> 25454.29 | H10: ='Daily Trade Summary'!L140 -> 4275.5592 | I10: ='Daily Trade Summary'!M140 -> 555.8227 | J10: ='Daily Trade Summary'!N140 -> 4831.3819 | K10: ='Daily Trade Summary'!O140 -> 20622.908 | L10: =IF($E10=0,"",$K10/$E10) -> 0.0015706574
A11: 46261 | B11: ='Daily Trade Summary'!B157 -> 26500 | C11: ='Daily Trade Summary'!E157 -> 26500 | D11: ='Daily Trade Summary'!I157 -> 0 | E11: ='Daily Trade Summary'!C157 -> 2407645 | F11: ='Daily Trade Summary'!F157 -> 2404525 | G11: ='Daily Trade Summary'!J157 -> -3120 | H11: ='Daily Trade Summary'!L157 -> 781.47063 | I11: ='Daily Trade Summary'!M157 -> 101.59118 | J11: ='Daily Trade Summary'!N157 -> 883.06181 | K11: ='Daily Trade Summary'!O157 -> -4003.0618 | L11: =IF($E11=0,"",$K11/$E11) -> -0.0016626462
A12: 46265 | B12: ='Daily Trade Summary'!B179 -> 51500 | C12: ='Daily Trade Summary'!E179 -> 51500 | D12: ='Daily Trade Summary'!I179 -> 0 | E12: ='Daily Trade Summary'!C179 -> 18280837 | F12: ='Daily Trade Summary'!F179 -> 18292560 | G12: ='Daily Trade Summary'!J179 -> 11723.11 | H12: ='Daily Trade Summary'!L179 -> 5945.082 | I12: ='Daily Trade Summary'!M179 -> 772.86066 | J12: ='Daily Trade Summary'!N179 -> 6717.9427 | K12: ='Daily Trade Summary'!O179 -> 5005.1673 | L12: =IF($E12=0,"",$K12/$E12) -> 0.00027379312
A13: 46266 | B13: ='Daily Trade Summary'!B203 -> 40920 | C13: ='Daily Trade Summary'!E203 -> 40920 | D13: ='Daily Trade Summary'!I203 -> 0 | E13: ='Daily Trade Summary'!C203 -> 13686449 | F13: ='Daily Trade Summary'!F203 -> 13711864 | G13: ='Daily Trade Summary'!J203 -> 25415.3 | H13: ='Daily Trade Summary'!L203 -> 4456.3559 | I13: ='Daily Trade Summary'!M203 -> 579.32627 | J13: ='Daily Trade Summary'!N203 -> 5035.6822 | K13: ='Daily Trade Summary'!O203 -> 20379.618 | L13: =IF($E13=0,"",$K13/$E13) -> 0.0014890362
A14: 46267 | B14: ='Daily Trade Summary'!B223 -> 115000 | C14: ='Daily Trade Summary'!E223 -> 115000 | D14: ='Daily Trade Summary'!I223 -> 0 | E14: ='Daily Trade Summary'!C223 -> 14853375 | F14: ='Daily Trade Summary'!F223 -> 14863825 | G14: ='Daily Trade Summary'!J223 -> 10450.36 | H14: ='Daily Trade Summary'!L223 -> 4830.7432 | I14: ='Daily Trade Summary'!M223 -> 627.99662 | J14: ='Daily Trade Summary'!N223 -> 5458.7399 | K14: ='Daily Trade Summary'!O223 -> 4991.6201 | L14: =IF($E14=0,"",$K14/$E14) -> 0.00033605966
A15: 46268 | B15: ='Daily Trade Summary'!B249 -> 85000 | C15: ='Daily Trade Summary'!E249 -> 85000 | D15: ='Daily Trade Summary'!I249 -> 0 | E15: ='Daily Trade Summary'!C249 -> 15859132 | F15: ='Daily Trade Summary'!F249 -> 15867402 | G15: ='Daily Trade Summary'!J249 -> 8269.59 | H15: ='Daily Trade Summary'!L249 -> 5156.9056 | I15: ='Daily Trade Summary'!M249 -> 670.39772 | J15: ='Daily Trade Summary'!N249 -> 5827.3033 | K15: ='Daily Trade Summary'!O249 -> 2442.2867 | L15: =IF($E15=0,"",$K15/$E15) -> 0.00015399876
A16: 46269 | B16: ='Daily Trade Summary'!B272 -> 139200 | C16: ='Daily Trade Summary'!E272 -> 139200 | D16: ='Daily Trade Summary'!I272 -> 0 | E16: ='Daily Trade Summary'!C272 -> 22870427 | F16: ='Daily Trade Summary'!F272 -> 22877215 | G16: ='Daily Trade Summary'!J272 -> 6788.43 | H16: ='Daily Trade Summary'!L272 -> 7435.0949 | I16: ='Daily Trade Summary'!M272 -> 966.56233 | J16: ='Daily Trade Summary'!N272 -> 8401.6572 | K16: ='Daily Trade Summary'!O272 -> -1613.2272 | L16: =IF($E16=0,"",$K16/$E16) -> -7.0537697e-05
A17: 46272 | B17: ='Daily Trade Summary'!B292 -> 22051 | C17: ='Daily Trade Summary'!E292 -> 22051 | D17: ='Daily Trade Summary'!I292 -> 0 | E17: ='Daily Trade Summary'!C292 -> 3194849.5 | F17: ='Daily Trade Summary'!F292 -> 3205253.5 | G17: ='Daily Trade Summary'!J292 -> 10403.97 | H17: ='Daily Trade Summary'!L292 -> 1041.7074 | I17: ='Daily Trade Summary'!M292 -> 135.42196 | J17: ='Daily Trade Summary'!N292 -> 1177.1293 | K17: ='Daily Trade Summary'!O292 -> 9226.8407 | L17: =IF($E17=0,"",$K17/$E17) -> 0.0028880361
A18: 46273 | B18: ='Daily Trade Summary'!B314 -> 67000 | C18: ='Daily Trade Summary'!E314 -> 67000 | D18: ='Daily Trade Summary'!I314 -> 0 | E18: ='Daily Trade Summary'!C314 -> 11580825 | F18: ='Daily Trade Summary'!F314 -> 11593195 | G18: ='Daily Trade Summary'!J314 -> 12370 | H18: ='Daily Trade Summary'!L314 -> 3716.4609 | I18: ='Daily Trade Summary'!M314 -> 483.13991 | J18: ='Daily Trade Summary'!N314 -> 4199.6008 | K18: ='Daily Trade Summary'!O314 -> 8170.3992 | L18: =IF($E18=0,"",$K18/$E18) -> 0.00070551098
A19: 46274 | B19: ='Daily Trade Summary'!B334 -> 51953 | C19: ='Daily Trade Summary'!E334 -> 51953 | D19: ='Daily Trade Summary'!I334 -> 0 | E19: ='Daily Trade Summary'!C334 -> 4936491 | F19: ='Daily Trade Summary'!F334 -> 4940816 | G19: ='Daily Trade Summary'!J334 -> 4324.98 | H19: ='Daily Trade Summary'!L334 -> 1605.7652 | I19: ='Daily Trade Summary'!M334 -> 208.74948 | J19: ='Daily Trade Summary'!N334 -> 1814.5147 | K19: ='Daily Trade Summary'!O334 -> 2510.4653 | L19: =IF($E19=0,"",$K19/$E19) -> 0.0005085526
A20: 46275 | B20: ='Daily Trade Summary'!B355 -> 25405 | C20: ='Daily Trade Summary'!E355 -> 25405 | D20: ='Daily Trade Summary'!I355 -> 0 | E20: ='Daily Trade Summary'!C355 -> 3843124.4 | F20: ='Daily Trade Summary'!F355 -> 3839233.9 | G20: ='Daily Trade Summary'!J355 -> -3890.53 | H20: ='Daily Trade Summary'!L355 -> 1189.7124 | I20: ='Daily Trade Summary'!M355 -> 154.66261 | J20: ='Daily Trade Summary'!N355 -> 1344.375 | K20: ='Daily Trade Summary'!O355 -> -5234.905 | L20: =IF($E20=0,"",$K20/$E20) -> -0.0013621482
A21: 46276 | B21: ='Daily Trade Summary'!B375 -> 52593 | C21: ='Daily Trade Summary'!E375 -> 52593 | D21: ='Daily Trade Summary'!I375 -> 0 | E21: ='Daily Trade Summary'!C375 -> 6080555.6 | F21: ='Daily Trade Summary'!F375 -> 6086289 | G21: ='Daily Trade Summary'!J375 -> 5733.48 | H21: ='Daily Trade Summary'!L375 -> 1978.0439 | I21: ='Daily Trade Summary'!M375 -> 257.14571 | J21: ='Daily Trade Summary'!N375 -> 2235.1897 | K21: ='Daily Trade Summary'!O375 -> 3498.2903 | L21: =IF($E21=0,"",$K21/$E21) -> 0.00057532413
A22: 46279 | B22: ='Daily Trade Summary'!B400 -> 68500 | C22: ='Daily Trade Summary'!E400 -> 68500 | D22: ='Daily Trade Summary'!I400 -> 0 | E22: ='Daily Trade Summary'!C400 -> 11322640 | F22: ='Daily Trade Summary'!F400 -> 11331895 | G22: ='Daily Trade Summary'!J400 -> 9254.58 | H22: ='Daily Trade Summary'!L400 -> 3682.8659 | I22: ='Daily Trade Summary'!M400 -> 478.77256 | J22: ='Daily Trade Summary'!N400 -> 4161.6384 | K22: ='Daily Trade Summary'!O400 -> 5092.9416 | L22: =IF($E22=0,"",$K22/$E22) -> 0.00044980158
A23: 46280 | B23: ='Daily Trade Summary'!B418 -> 18000 | C23: ='Daily Trade Summary'!E418 -> 18000 | D23: ='Daily Trade Summary'!I418 -> 0 | E23: ='Daily Trade Summary'!C418 -> 2928580 | F23: ='Daily Trade Summary'!F418 -> 2930140 | G23: ='Daily Trade Summary'!J418 -> 1560 | H23: ='Daily Trade Summary'!L418 -> 952.2955 | I23: ='Daily Trade Summary'!M418 -> 123.79842 | J23: ='Daily Trade Summary'!N418 -> 1076.0939 | K23: ='Daily Trade Summary'!O418 -> 483.90609 | L23: =IF($E23=0,"",$K23/$E23) -> 0.00016523574
A24: 46281 | B24: ='Daily Trade Summary'!B442 -> 43500 | C24: ='Daily Trade Summary'!E442 -> 43500 | D24: ='Daily Trade Summary'!I442 -> 0 | E24: ='Daily Trade Summary'!C442 -> 8237815.7 | F24: ='Daily Trade Summary'!F442 -> 8236390 | G24: ='Daily Trade Summary'!J442 -> -1425.65 | H24: ='Daily Trade Summary'!L442 -> 2676.8268 | I24: ='Daily Trade Summary'!M442 -> 347.98748 | J24: ='Daily Trade Summary'!N442 -> 3024.8142 | K24: ='Daily Trade Summary'!O442 -> -4450.4642 | L24: =IF($E24=0,"",$K24/$E24) -> -0.0005402481
A25: 46282 | B25: ='Daily Trade Summary'!B468 -> 57500 | C25: ='Daily Trade Summary'!E468 -> 57500 | D25: ='Daily Trade Summary'!I468 -> 0 | E25: ='Daily Trade Summary'!C468 -> 10564945 | F25: ='Daily Trade Summary'!F468 -> 10567938 | G25: ='Daily Trade Summary'!J468 -> 2992.65 | H25: ='Daily Trade Summary'!L468 -> 3434.5797 | I25: ='Daily Trade Summary'!M468 -> 446.49537 | J25: ='Daily Trade Summary'!N468 -> 3881.0751 | K25: ='Daily Trade Summary'!O468 -> -888.4251 | L25: =IF($E25=0,"",$K25/$E25) -> -8.4091787e-05
A26: 46283 | B26: ='Daily Trade Summary'!B495 -> 94719 | C26: ='Daily Trade Summary'!E495 -> 94719 | D26: ='Daily Trade Summary'!I495 -> 0 | E26: ='Daily Trade Summary'!C495 -> 14436906 | F26: ='Daily Trade Summary'!F495 -> 14447051 | G26: ='Daily Trade Summary'!J495 -> 10145.52 | H26: ='Daily Trade Summary'!L495 -> 4695.2917 | I26: ='Daily Trade Summary'!M495 -> 610.38792 | J26: ='Daily Trade Summary'!N495 -> 5305.6796 | K26: ='Daily Trade Summary'!O495 -> 4839.8404 | L26: =IF($E26=0,"",$K26/$E26) -> 0.00033524083
A27: 46293 | B27: ='Daily Trade Summary'!B521 -> 143000 | C27: ='Daily Trade Summary'!E521 -> 143000 | D27: ='Daily Trade Summary'!I521 -> 0 | E27: ='Daily Trade Summary'!C521 -> 15324771 | F27: ='Daily Trade Summary'!F521 -> 15336029 | G27: ='Daily Trade Summary'!J521 -> 11258.44 | H27: ='Daily Trade Summary'!L521 -> 4771.0938 | I27: ='Daily Trade Summary'!M521 -> 620.2422 | J27: ='Daily Trade Summary'!N521 -> 5391.336 | K27: ='Daily Trade Summary'!O521 -> 5867.104 | L27: =IF($E27=0,"",$K27/$E27) -> 0.00038285101
A28: 46294 | B28: ='Daily Trade Summary'!B542 -> 97000 | C28: ='Daily Trade Summary'!E542 -> 97000 | D28: ='Daily Trade Summary'!I542 -> 0 | E28: ='Daily Trade Summary'!C542 -> 12460825 | F28: ='Daily Trade Summary'!F542 -> 12473955 | G28: ='Daily Trade Summary'!J542 -> 13130 | H28: ='Daily Trade Summary'!L542 -> 4006.7798 | I28: ='Daily Trade Summary'!M542 -> 520.88137 | J28: ='Daily Trade Summary'!N542 -> 4527.6611 | K28: ='Daily Trade Summary'!O542 -> 8602.3389 | L28: =IF($E28=0,"",$K28/$E28) -> 0.00069035067
A29: 46295 | B29: ='Daily Trade Summary'!B563 -> 114485 | C29: ='Daily Trade Summary'!E563 -> 114485 | D29: ='Daily Trade Summary'!I563 -> 0 | E29: ='Daily Trade Summary'!C563 -> 13933421 | F29: ='Daily Trade Summary'!F563 -> 13941808 | G29: ='Daily Trade Summary'!J563 -> 8387.2 | H29: ='Daily Trade Summary'!L563 -> 4531.0876 | I29: ='Daily Trade Summary'!M563 -> 589.04139 | J29: ='Daily Trade Summary'!N563 -> 5120.129 | K29: ='Daily Trade Summary'!O563 -> 3267.071 | L29: =IF($E29=0,"",$K29/$E29) -> 0.0002344773
A30: 46296 | B30: ='Daily Trade Summary'!B585 -> 61500 | C30: ='Daily Trade Summary'!E585 -> 61500 | D30: ='Daily Trade Summary'!I585 -> 0 | E30: ='Daily Trade Summary'!C585 -> 9592760 | F30: ='Daily Trade Summary'!F585 -> 9603580 | G30: ='Daily Trade Summary'!J585 -> 10820 | H30: ='Daily Trade Summary'!L585 -> 3121.1635 | I30: ='Daily Trade Summary'!M585 -> 405.75126 | J30: ='Daily Trade Summary'!N585 -> 3526.9148 | K30: ='Daily Trade Summary'!O585 -> 7293.0852 | L30: =IF($E30=0,"",$K30/$E30) -> 0.00076026975
A31: 46297 | B31: ='Daily Trade Summary'!B605 -> 35500 | C31: ='Daily Trade Summary'!E605 -> 35500 | D31: ='Daily Trade Summary'!I605 -> 0 | E31: ='Daily Trade Summary'!C605 -> 8710670 | F31: ='Daily Trade Summary'!F605 -> 8714260 | G31: ='Daily Trade Summary'!J605 -> 3590 | H31: ='Daily Trade Summary'!L605 -> 2832.1345 | I31: ='Daily Trade Summary'!M605 -> 368.17748 | J31: ='Daily Trade Summary'!N605 -> 3200.312 | K31: ='Daily Trade Summary'!O605 -> 389.68802 | L31: =IF($E31=0,"",$K31/$E31) -> 4.4736859e-05
A32: 46300 | B32: ='Daily Trade Summary'!B625 -> 60000 | C32: ='Daily Trade Summary'!E625 -> 60000 | D32: ='Daily Trade Summary'!I625 -> 0 | E32: ='Daily Trade Summary'!C625 -> 6890615 | F32: ='Daily Trade Summary'!F625 -> 6893846.3 | G32: ='Daily Trade Summary'!J625 -> 3231.33 | H32: ='Daily Trade Summary'!L625 -> 2240.5001 | I32: ='Daily Trade Summary'!M625 -> 291.26501 | J32: ='Daily Trade Summary'!N625 -> 2531.7651 | K32: ='Daily Trade Summary'!O625 -> 699.56494 | L32: =IF($E32=0,"",$K32/$E32) -> 0.00010152431
A33: 46301 | B33: ='Daily Trade Summary'!B652 -> 126235 | C33: ='Daily Trade Summary'!E652 -> 126235 | D33: ='Daily Trade Summary'!I652 -> 0 | E33: ='Daily Trade Summary'!C652 -> 19094354 | F33: ='Daily Trade Summary'!F652 -> 19099591 | G33: ='Daily Trade Summary'!J652 -> 5237.26 | H33: ='Daily Trade Summary'!L652 -> 5871.6662 | I33: ='Daily Trade Summary'!M652 -> 763.31661 | J33: ='Daily Trade Summary'!N652 -> 6634.9828 | K33: ='Daily Trade Summary'!O652 -> -1397.7228 | L33: =IF($E33=0,"",$K33/$E33) -> -7.3200846e-05
A34: 46302 | B34: ='Daily Trade Summary'!B678 -> 114400 | C34: ='Daily Trade Summary'!E678 -> 114400 | D34: ='Daily Trade Summary'!I678 -> 0 | E34: ='Daily Trade Summary'!C678 -> 15990980 | F34: ='Daily Trade Summary'!F678 -> 16004711 | G34: ='Daily Trade Summary'!J678 -> 13730.84 | H34: ='Daily Trade Summary'!L678 -> 5201.5311 | I34: ='Daily Trade Summary'!M678 -> 676.19904 | J34: ='Daily Trade Summary'!N678 -> 5877.7301 | K34: ='Daily Trade Summary'!O678 -> 7853.1099 | L34: =IF($E34=0,"",$K34/$E34) -> 0.00049109622
A35: 46303 | B35: ='Daily Trade Summary'!B700 -> 62859 | C35: ='Daily Trade Summary'!E700 -> 62859 | D35: ='Daily Trade Summary'!I700 -> 0 | E35: ='Daily Trade Summary'!C700 -> 9701743.2 | F35: ='Daily Trade Summary'!F700 -> 9715115.4 | G35: ='Daily Trade Summary'!J700 -> 13372.19 | H35: ='Daily Trade Summary'!L700 -> 3157.4125 | I35: ='Daily Trade Summary'!M700 -> 410.46363 | J35: ='Daily Trade Summary'!N700 -> 3567.8761 | K35: ='Daily Trade Summary'!O700 -> 9804.3139 | L35: =IF($E35=0,"",$K35/$E35) -> 0.0010105724
A36: 46304 | B36: ='Daily Trade Summary'!B718 -> 28000 | C36: ='Daily Trade Summary'!E718 -> 28000 | D36: ='Daily Trade Summary'!I718 -> 0 | E36: ='Daily Trade Summary'!C718 -> 3975465 | F36: ='Daily Trade Summary'!F718 -> 3982225 | G36: ='Daily Trade Summary'!J718 -> 6760 | H36: ='Daily Trade Summary'!L718 -> 1294.2231 | I36: ='Daily Trade Summary'!M718 -> 168.24901 | J36: ='Daily Trade Summary'!N718 -> 1462.4721 | K36: ='Daily Trade Summary'!O718 -> 5297.5279 | L36: =IF($E36=0,"",$K36/$E36) -> 0.0013325555
A37: 46307 | B37: ='Daily Trade Summary'!B741 -> 119500 | C37: ='Daily Trade Summary'!E741 -> 119500 | D37: ='Daily Trade Summary'!I741 -> 0 | E37: ='Daily Trade Summary'!C741 -> 13087568 | F37: ='Daily Trade Summary'!F741 -> 13093430 | G37: ='Daily Trade Summary'!J741 -> 5862 | H37: ='Daily Trade Summary'!L741 -> 4088.782 | I37: ='Daily Trade Summary'!M741 -> 531.54166 | J37: ='Daily Trade Summary'!N741 -> 4620.3237 | K37: ='Daily Trade Summary'!O741 -> 1241.6763 | L37: =IF($E37=0,"",$K37/$E37) -> 9.487449e-05
A38: 46308 | B38: ='Daily Trade Summary'!B761 -> 111000 | C38: ='Daily Trade Summary'!E761 -> 111000 | D38: ='Daily Trade Summary'!I761 -> 0 | E38: ='Daily Trade Summary'!C761 -> 8618263 | F38: ='Daily Trade Summary'!F761 -> 8617447 | G38: ='Daily Trade Summary'!J761 -> -816 | H38: ='Daily Trade Summary'!L761 -> 2112.7472 | I38: ='Daily Trade Summary'!M761 -> 274.65713 | J38: ='Daily Trade Summary'!N761 -> 2387.4043 | K38: ='Daily Trade Summary'!O761 -> -3203.4043 | L38: =IF($E38=0,"",$K38/$E38) -> -0.00037169953
A39: 46310 | B39: ='Daily Trade Summary'!B782 -> 72500 | C39: ='Daily Trade Summary'!E782 -> 72500 | D39: ='Daily Trade Summary'!I782 -> 0 | E39: ='Daily Trade Summary'!C782 -> 11671305 | F39: ='Daily Trade Summary'!F782 -> 11678640 | G39: ='Daily Trade Summary'!J782 -> 7335 | H39: ='Daily Trade Summary'!L782 -> 3795.558 | I39: ='Daily Trade Summary'!M782 -> 493.42254 | J39: ='Daily Trade Summary'!N782 -> 4288.9805 | K39: ='Daily Trade Summary'!O782 -> 3046.0195 | L39: =IF($E39=0,"",$K39/$E39) -> 0.00026098362
A40: 46311 | B40: ='Daily Trade Summary'!B803 -> 22500 | C40: ='Daily Trade Summary'!E803 -> 22500 | D40: ='Daily Trade Summary'!I803 -> 0 | E40: ='Daily Trade Summary'!C803 -> 4845060 | F40: ='Daily Trade Summary'!F803 -> 4855610 | G40: ='Daily Trade Summary'!J803 -> 10550 | H40: ='Daily Trade Summary'!L803 -> 1578.0732 | I40: ='Daily Trade Summary'!M803 -> 205.14952 | J40: ='Daily Trade Summary'!N803 -> 1783.2228 | K40: ='Daily Trade Summary'!O803 -> 8766.7772 | L40: =IF($E40=0,"",$K40/$E40) -> 0.0018094259
A41: TOTAL | B41: =SUM(B5:B40) -> 2612821 | C41: =SUM(C5:C40) -> 2612821 | D41: =$B41-$C41 -> 0 | E41: =SUM(E5:E40) -> 4.0323137e+08 | F41: =SUM(F5:F40) -> 4.0357074e+08 | G41: =SUM(G5:G40) -> 339374.14 | H41: =SUM(H5:H40) -> 129301.35 | I41: =SUM(I5:I40) -> 16809.176 | J41: =SUM(J5:J40) -> 146110.53 | K41: =SUM(K5:K40) -> 193263.61 | L41: =IF($E41=0,"",$K41/$E41) -> 0.00047928714

Sheet MTD Summary
A1: Month-to-Date — October 2026
A2: Live SUMIFS over the Daily Summary, bounded by the period dates below.
A4: Period Start (calendar): | B4: 46296
A5: Period End (latest trade): | B5: =MAX('Daily Summary'!$A$5:$A$404) -> 46311
A6: First Trading Day in Period: | B6: =IFERROR(IF(INDEX('Daily Summary'!$A$5:$A$404,COUNTIF('Daily Summary'!$A$5:$A$404,"<"&$B$4)+1)>$B$5,"—",INDEX('Daily Summary'!$A$5:$A$404,COUNTIF('Daily Summary'!$A$5:$A$404,"<"&$B$4)+1)),"—") -> 46296
A7: Trading Days: | B7: =COUNTIFS('Daily Summary'!$A$5:$A$404,">="&$B$4,'Daily Summary'!$A$5:$A$404,"<="&$B$5) -> 11
A9: Metric | B9: Value
A10: Buy Quantity | B10: =SUMIFS('Daily Summary'!$B$5:$B$404,'Daily Summary'!$A$5:$A$404,">="&$B$4,'Daily Summary'!$A$5:$A$404,"<="&$B$5) -> 813994
A11: Sell Quantity | B11: =SUMIFS('Daily Summary'!$C$5:$C$404,'Daily Summary'!$A$5:$A$404,">="&$B$4,'Daily Summary'!$A$5:$A$404,"<="&$B$5) -> 813994
A12: Net Quantity | B12: =SUMIFS('Daily Summary'!$D$5:$D$404,'Daily Summary'!$A$5:$A$404,">="&$B$4,'Daily Summary'!$A$5:$A$404,"<="&$B$5) -> 0
A13: Buy Value (PKR) | B13: =SUMIFS('Daily Summary'!$E$5:$E$404,'Daily Summary'!$A$5:$A$404,">="&$B$4,'Daily Summary'!$A$5:$A$404,"<="&$B$5) -> 1.1217878e+08
A14: Sell Value (PKR) | B14: =SUMIFS('Daily Summary'!$F$5:$F$404,'Daily Summary'!$A$5:$A$404,">="&$B$4,'Daily Summary'!$A$5:$A$404,"<="&$B$5) -> 1.1225846e+08
A15: Gross P&L (PKR) | B15: =SUMIFS('Daily Summary'!$G$5:$G$404,'Daily Summary'!$A$5:$A$404,">="&$B$4,'Daily Summary'!$A$5:$A$404,"<="&$B$5) -> 79672.62
A16: Commission (PKR) | B16: =SUMIFS('Daily Summary'!$H$5:$H$404,'Daily Summary'!$A$5:$A$404,">="&$B$4,'Daily Summary'!$A$5:$A$404,"<="&$B$5) -> 35293.791
A17: SST (PKR) | B17: =SUMIFS('Daily Summary'!$I$5:$I$404,'Daily Summary'!$A$5:$A$404,">="&$B$4,'Daily Summary'!$A$5:$A$404,"<="&$B$5) -> 4588.1929
A18: Total Charges (PKR) | B18: =SUMIFS('Daily Summary'!$J$5:$J$404,'Daily Summary'!$A$5:$A$404,">="&$B$4,'Daily Summary'!$A$5:$A$404,"<="&$B$5) -> 39881.984
A19: Net P&L (PKR) | B19: =SUMIFS('Daily Summary'!$K$5:$K$404,'Daily Summary'!$A$5:$A$404,">="&$B$4,'Daily Summary'!$A$5:$A$404,"<="&$B$5) -> 39790.636
A20: Return on Buy | B20: =IF($B$13=0,"",$B$19/$B$13) -> 0.00035470732
A22: Date-by-Date Breakdown
A23: Date | B23: Buy Qty | C23: Sell Qty | D23: Net Qty | E23: Buy Value (PKR) | F23: Sell Value (PKR) | G23: Gross P&L (PKR) | H23: Commission (PKR) | I23: SST (PKR) | J23: Total Charges (PKR) | K23: Net P&L (PKR) | L23: Return on Buy
A24: ='Daily Summary'!A30 -> 46296 | B24: ='Daily Summary'!B30 -> 61500 | C24: ='Daily Summary'!C30 -> 61500 | D24: ='Daily Summary'!D30 -> 0 | E24: ='Daily Summary'!E30 -> 9592760 | F24: ='Daily Summary'!F30 -> 9603580 | G24: ='Daily Summary'!G30 -> 10820 | H24: ='Daily Summary'!H30 -> 3121.1635 | ... L24: ='Daily Summary'!L30 -> 0.00076026975
A25: ='Daily Summary'!A31 -> 46297 | B25: ='Daily Summary'!B31 -> 35500 | C25: ='Daily Summary'!C31 -> 35500 | D25: ='Daily Summary'!D31 -> 0 | E25: ='Daily Summary'!E31 -> 8710670 | F25: ='Daily Summary'!F31 -> 8714260 | G25: ='Daily Summary'!G31 -> 3590 | H25: ='Daily Summary'!H31 -> 2832.1345 | ... L25: ='Daily Summary'!L31 -> 4.4736859e-05
A26: ='Daily Summary'!A32 -> 46300 | B26: ='Daily Summary'!B32 -> 60000 | C26: ='Daily Summary'!C32 -> 60000 | D26: ='Daily Summary'!D32 -> 0 | E26: ='Daily Summary'!E32 -> 6890615 | F26: ='Daily Summary'!F32 -> 6893846.3 | G26: ='Daily Summary'!G32 -> 3231.33 | H26: ='Daily Summary'!H32 -> 2240.5001 | ... L26: ='Daily Summary'!L32 -> 0.00010152431
A27: ='Daily Summary'!A33 -> 46301 | B27: ='Daily Summary'!B33 -> 126235 | C27: ='Daily Summary'!C33 -> 126235 | D27: ='Daily Summary'!D33 -> 0 | E27: ='Daily Summary'!E33 -> 19094354 | F27: ='Daily Summary'!F33 -> 19099591 | G27: ='Daily Summary'!G33 -> 5237.26 | H27: ='Daily Summary'!H33 -> 5871.6662 | ... L27: ='Daily Summary'!L33 -> -7.3200846e-05
A28: ='Daily Summary'!A34 -> 46302 | B28: ='Daily Summary'!B34 -> 114400 | C28: ='Daily Summary'!C34 -> 114400 | D28: ='Daily Summary'!D34 -> 0 | E28: ='Daily Summary'!E34 -> 15990980 | F28: ='Daily Summary'!F34 -> 16004711 | G28: ='Daily Summary'!G34 -> 13730.84 | H28: ='Daily Summary'!H34 -> 5201.5311 | ... L28: ='Daily Summary'!L34 -> 0.00049109622
A29: ='Daily Summary'!A35 -> 46303 | B29: ='Daily Summary'!B35 -> 62859 | C29: ='Daily Summary'!C35 -> 62859 | D29: ='Daily Summary'!D35 -> 0 | E29: ='Daily Summary'!E35 -> 9701743.2 | F29: ='Daily Summary'!F35 -> 9715115.4 | G29: ='Daily Summary'!G35 -> 13372.19 | H29: ='Daily Summary'!H35 -> 3157.4125 | ... L29: ='Daily Summary'!L35 -> 0.0010105724
A30: ='Daily Summary'!A36 -> 46304 | B30: ='Daily Summary'!B36 -> 28000 | C30: ='Daily Summary'!C36 -> 28000 | D30: ='Daily Summary'!D36 -> 0 | E30: ='Daily Summary'!E36 -> 3975465 | F30: ='Daily Summary'!F36 -> 3982225 | G30: ='Daily Summary'!G36 -> 6760 | H30: ='Daily Summary'!H36 -> 1294.2231 | ... L30: ='Daily Summary'!L36 -> 0.0013325555
A31: ='Daily Summary'!A37 -> 46307 | B31: ='Daily Summary'!B37 -> 119500 | C31: ='Daily Summary'!C37 -> 119500 | D31: ='Daily Summary'!D37 -> 0 | E31: ='Daily Summary'!E37 -> 13087568 | F31: ='Daily Summary'!F37 -> 13093430 | G31: ='Daily Summary'!G37 -> 5862 | H31: ='Daily Summary'!H37 -> 4088.782 | ... L31: ='Daily Summary'!L37 -> 9.487449e-05
A32: ='Daily Summary'!A38 -> 46308 | B32: ='Daily Summary'!B38 -> 111000 | C32: ='Daily Summary'!C38 -> 111000 | D32: ='Daily Summary'!D38 -> 0 | E32: ='Daily Summary'!E38 -> 8618263 | F32: ='Daily Summary'!F38 -> 8617447 | G32: ='Daily Summary'!G38 -> -816 | H32: ='Daily Summary'!H38 -> 2112.7472 | ... L32: ='Daily Summary'!L38 -> -0.00037169953
A33: ='Daily Summary'!A39 -> 46310 | B33: ='Daily Summary'!B39 -> 72500 | C33: ='Daily Summary'!C39 -> 72500 | D33: ='Daily Summary'!D39 -> 0 | E33: ='Daily Summary'!E39 -> 11671305 | F33: ='Daily Summary'!F39 -> 11678640 | G33: ='Daily Summary'!G39 -> 7335 | H33: ='Daily Summary'!H39 -> 3795.558 | ... L33: ='Daily Summary'!L39 -> 0.00026098362
A34: ='Daily Summary'!A40 -> 46311 | B34: ='Daily Summary'!B40 -> 22500 | C34: ='Daily Summary'!C40 -> 22500 | D34: ='Daily Summary'!D40 -> 0 | E34: ='Daily Summary'!E40 -> 4845060 | F34: ='Daily Summary'!F40 -> 4855610 | G34: ='Daily Summary'!G40 -> 10550 | H34: ='Daily Summary'!H40 -> 1578.0732 | ... L34: ='Daily Summary'!L40 -> 0.0018094259
A35: TOTAL | B35: =SUM(B24:B34) -> 813994 | C35: =SUM(C24:C34) -> 813994 | D35: =$B35-$C35 -> 0 | E35: =SUM(E24:E34) -> 1.1217878e+08 | F35: =SUM(F24:F34) -> 1.1225846e+08 | G35: =SUM(G24:G34) -> 79672.62 | H35: =SUM(H24:H34) -> 35293.791 | I35: =SUM(I24:I34) -> 4588.1929 | J35: =SUM(J24:J34) -> 39881.984 | K35: =SUM(K24:K34) -> 39790.636 | L35: =IF($E35=0,"",$K35/$E35) -> 0.00035470732

Sheet QTD Summary
A1: Quarter-to-Date — Q4 2026 (Oct–Dec)
A2: Live SUMIFS over the Daily Summary, bounded by the period dates below.
A4: Period Start (calendar): | B4: 46296
A5: Period End (latest trade): | B5: =MAX('Daily Summary'!$A$5:$A$404) -> 46311
A6: First Trading Day in Period: | B6: =IFERROR(IF(INDEX('Daily Summary'!$A$5:$A$404,COUNTIF('Daily Summary'!$A$5:$A$404,"<"&$B$4)+1)>$B$5,"—",INDEX('Daily Summary'!$A$5:$A$404,COUNTIF('Daily Summary'!$A$5:$A$404,"<"&$B$4)+1)),"—") -> 46296
A7: Trading Days: | B7: =COUNTIFS('Daily Summary'!$A$5:$A$404,">="&$B$4,'Daily Summary'!$A$5:$A$404,"<="&$B$5) -> 11
A9: Metric | B9: Value
A10: Buy Quantity | B10: =SUMIFS('Daily Summary'!$B$5:$B$404,'Daily Summary'!$A$5:$A$404,">="&$B$4,'Daily Summary'!$A$5:$A$404,"<="&$B$5) -> 813994
A11: Sell Quantity | B11: =SUMIFS('Daily Summary'!$C$5:$C$404,'Daily Summary'!$A$5:$A$404,">="&$B$4,'Daily Summary'!$A$5:$A$404,"<="&$B$5) -> 813994
A12: Net Quantity | B12: =SUMIFS('Daily Summary'!$D$5:$D$404,'Daily Summary'!$A$5:$A$404,">="&$B$4,'Daily Summary'!$A$5:$A$404,"<="&$B$5) -> 0
A13: Buy Value (PKR) | B13: =SUMIFS('Daily Summary'!$E$5:$E$404,'Daily Summary'!$A$5:$A$404,">="&$B$4,'Daily Summary'!$A$5:$A$404,"<="&$B$5) -> 1.1217878e+08
A14: Sell Value (PKR) | B14: =SUMIFS('Daily Summary'!$F$5:$F$404,'Daily Summary'!$A$5:$A$404,">="&$B$4,'Daily Summary'!$A$5:$A$404,"<="&$B$5) -> 1.1225846e+08
A15: Gross P&L (PKR) | B15: =SUMIFS('Daily Summary'!$G$5:$G$404,'Daily Summary'!$A$5:$A$404,">="&$B$4,'Daily Summary'!$A$5:$A$404,"<="&$B$5) -> 79672.62
A16: Commission (PKR) | B16: =SUMIFS('Daily Summary'!$H$5:$H$404,'Daily Summary'!$A$5:$A$404,">="&$B$4,'Daily Summary'!$A$5:$A$404,"<="&$B$5) -> 35293.791
A17: SST (PKR) | B17: =SUMIFS('Daily Summary'!$I$5:$I$404,'Daily Summary'!$A$5:$A$404,">="&$B$4,'Daily Summary'!$A$5:$A$404,"<="&$B$5) -> 4588.1929
A18: Total Charges (PKR) | B18: =SUMIFS('Daily Summary'!$J$5:$J$404,'Daily Summary'!$A$5:$A$404,">="&$B$4,'Daily Summary'!$A$5:$A$404,"<="&$B$5) -> 39881.984
A19: Net P&L (PKR) | B19: =SUMIFS('Daily Summary'!$K$5:$K$404,'Daily Summary'!$A$5:$A$404,">="&$B$4,'Daily Summary'!$A$5:$A$404,"<="&$B$5) -> 39790.636
A20: Return on Buy | B20: =IF($B$13=0,"",$B$19/$B$13) -> 0.00035470732
A22: Date-by-Date Breakdown
A23: Date | B23: Buy Qty | C23: Sell Qty | D23: Net Qty | E23: Buy Value (PKR) | F23: Sell Value (PKR) | G23: Gross P&L (PKR) | H23: Commission (PKR) | I23: SST (PKR) | J23: Total Charges (PKR) | K23: Net P&L (PKR) | L23: Return on Buy
A24: ='Daily Summary'!A30 -> 46296 | B24: ='Daily Summary'!B30 -> 61500 | C24: ='Daily Summary'!C30 -> 61500 | D24: ='Daily Summary'!D30 -> 0 | E24: ='Daily Summary'!E30 -> 9592760 | F24: ='Daily Summary'!F30 -> 9603580 | G24: ='Daily Summary'!G30 -> 10820 | H24: ='Daily Summary'!H30 -> 3121.1635 | ... L24: ='Daily Summary'!L30 -> 0.00076026975
A25: ='Daily Summary'!A31 -> 46297 | B25: ='Daily Summary'!B31 -> 35500 | C25: ='Daily Summary'!C31 -> 35500 | D25: ='Daily Summary'!D31 -> 0 | E25: ='Daily Summary'!E31 -> 8710670 | F25: ='Daily Summary'!F31 -> 8714260 | G25: ='Daily Summary'!G31 -> 3590 | H25: ='Daily Summary'!H31 -> 2832.1345 | ... L25: ='Daily Summary'!L31 -> 4.4736859e-05
A26: ='Daily Summary'!A32 -> 46300 | B26: ='Daily Summary'!B32 -> 60000 | C26: ='Daily Summary'!C32 -> 60000 | D26: ='Daily Summary'!D32 -> 0 | E26: ='Daily Summary'!E32 -> 6890615 | F26: ='Daily Summary'!F32 -> 6893846.3 | G26: ='Daily Summary'!G32 -> 3231.33 | H26: ='Daily Summary'!H32 -> 2240.5001 | ... L26: ='Daily Summary'!L32 -> 0.00010152431
A27: ='Daily Summary'!A33 -> 46301 | B27: ='Daily Summary'!B33 -> 126235 | C27: ='Daily Summary'!C33 -> 126235 | D27: ='Daily Summary'!D33 -> 0 | E27: ='Daily Summary'!E33 -> 19094354 | F27: ='Daily Summary'!F33 -> 19099591 | G27: ='Daily Summary'!G33 -> 5237.26 | H27: ='Daily Summary'!H33 -> 5871.6662 | ... L27: ='Daily Summary'!L33 -> -7.3200846e-05
A28: ='Daily Summary'!A34 -> 46302 | B28: ='Daily Summary'!B34 -> 114400 | C28: ='Daily Summary'!C34 -> 114400 | D28: ='Daily Summary'!D34 -> 0 | E28: ='Daily Summary'!E34 -> 15990980 | F28: ='Daily Summary'!F34 -> 16004711 | G28: ='Daily Summary'!G34 -> 13730.84 | H28: ='Daily Summary'!H34 -> 5201.5311 | ... L28: ='Daily Summary'!L34 -> 0.00049109622
A29: ='Daily Summary'!A35 -> 46303 | B29: ='Daily Summary'!B35 -> 62859 | C29: ='Daily Summary'!C35 -> 62859 | D29: ='Daily Summary'!D35 -> 0 | E29: ='Daily Summary'!E35 -> 9701743.2 | F29: ='Daily Summary'!F35 -> 9715115.4 | G29: ='Daily Summary'!G35 -> 13372.19 | H29: ='Daily Summary'!H35 -> 3157.4125 | ... L29: ='Daily Summary'!L35 -> 0.0010105724
A30: ='Daily Summary'!A36 -> 46304 | B30: ='Daily Summary'!B36 -> 28000 | C30: ='Daily Summary'!C36 -> 28000 | D30: ='Daily Summary'!D36 -> 0 | E30: ='Daily Summary'!E36 -> 3975465 | F30: ='Daily Summary'!F36 -> 3982225 | G30: ='Daily Summary'!G36 -> 6760 | H30: ='Daily Summary'!H36 -> 1294.2231 | ... L30: ='Daily Summary'!L36 -> 0.0013325555
A31: ='Daily Summary'!A37 -> 46307 | B31: ='Daily Summary'!B37 -> 119500 | C31: ='Daily Summary'!C37 -> 119500 | D31: ='Daily Summary'!D37 -> 0 | E31: ='Daily Summary'!E37 -> 13087568 | F31: ='Daily Summary'!F37 -> 13093430 | G31: ='Daily Summary'!G37 -> 5862 | H31: ='Daily Summary'!H37 -> 4088.782 | ... L31: ='Daily Summary'!L37 -> 9.487449e-05
A32: ='Daily Summary'!A38 -> 46308 | B32: ='Daily Summary'!B38 -> 111000 | C32: ='Daily Summary'!C38 -> 111000 | D32: ='Daily Summary'!D38 -> 0 | E32: ='Daily Summary'!E38 -> 8618263 | F32: ='Daily Summary'!F38 -> 8617447 | G32: ='Daily Summary'!G38 -> -816 | H32: ='Daily Summary'!H38 -> 2112.7472 | ... L32: ='Daily Summary'!L38 -> -0.00037169953
A33: ='Daily Summary'!A39 -> 46310 | B33: ='Daily Summary'!B39 -> 72500 | C33: ='Daily Summary'!C39 -> 72500 | D33: ='Daily Summary'!D39 -> 0 | E33: ='Daily Summary'!E39 -> 11671305 | F33: ='Daily Summary'!F39 -> 11678640 | G33: ='Daily Summary'!G39 -> 7335 | H33: ='Daily Summary'!H39 -> 3795.558 | ... L33: ='Daily Summary'!L39 -> 0.00026098362
A34: ='Daily Summary'!A40 -> 46311 | B34: ='Daily Summary'!B40 -> 22500 | C34: ='Daily Summary'!C40 -> 22500 | D34: ='Daily Summary'!D40 -> 0 | E34: ='Daily Summary'!E40 -> 4845060 | F34: ='Daily Summary'!F40 -> 4855610 | G34: ='Daily Summary'!G40 -> 10550 | H34: ='Daily Summary'!H40 -> 1578.0732 | ... L34: ='Daily Summary'!L40 -> 0.0018094259
A35: TOTAL | B35: =SUM(B24:B34) -> 813994 | C35: =SUM(C24:C34) -> 813994 | D35: =$B35-$C35 -> 0 | E35: =SUM(E24:E34) -> 1.1217878e+08 | F35: =SUM(F24:F34) -> 1.1225846e+08 | G35: =SUM(G24:G34) -> 79672.62 | H35: =SUM(H24:H34) -> 35293.791 | I35: =SUM(I24:I34) -> 4588.1929 | J35: =SUM(J24:J34) -> 39881.984 | K35: =SUM(K24:K34) -> 39790.636 | L35: =IF($E35=0,"",$K35/$E35) -> 0.00035470732

Sheet YTD Summary
A1: Year-to-Date — 2026
A2: Live SUMIFS over the Daily Summary, bounded by the period dates below.
A4: Period Start (calendar): | B4: 46023
A5: Period End (latest trade): | B5: =MAX('Daily Summary'!$A$5:$A$404) -> 46311
A6: First Trading Day in Period: | B6: =IFERROR(IF(INDEX('Daily Summary'!$A$5:$A$404,COUNTIF('Daily Summary'!$A$5:$A$404,"<"&$B$4)+1)>$B$5,"—",INDEX('Daily Summary'!$A$5:$A$404,COUNTIF('Daily Summary'!$A$5:$A$404,"<"&$B$4)+1)),"—") -> 46251
A7: Trading Days: | B7: =COUNTIFS('Daily Summary'!$A$5:$A$404,">="&$B$4,'Daily Summary'!$A$5:$A$404,"<="&$B$5) -> 36
A9: Metric | B9: Value
A10: Buy Quantity | B10: =SUMIFS('Daily Summary'!$B$5:$B$404,'Daily Summary'!$A$5:$A$404,">="&$B$4,'Daily Summary'!$A$5:$A$404,"<="&$B$5) -> 2612821
A11: Sell Quantity | B11: =SUMIFS('Daily Summary'!$C$5:$C$404,'Daily Summary'!$A$5:$A$404,">="&$B$4,'Daily Summary'!$A$5:$A$404,"<="&$B$5) -> 2612821
A12: Net Quantity | B12: =SUMIFS('Daily Summary'!$D$5:$D$404,'Daily Summary'!$A$5:$A$404,">="&$B$4,'Daily Summary'!$A$5:$A$404,"<="&$B$5) -> 0
A13: Buy Value (PKR) | B13: =SUMIFS('Daily Summary'!$E$5:$E$404,'Daily Summary'!$A$5:$A$404,">="&$B$4,'Daily Summary'!$A$5:$A$404,"<="&$B$5) -> 4.0323137e+08
A14: Sell Value (PKR) | B14: =SUMIFS('Daily Summary'!$F$5:$F$404,'Daily Summary'!$A$5:$A$404,">="&$B$4,'Daily Summary'!$A$5:$A$404,"<="&$B$5) -> 4.0357074e+08
A15: Gross P&L (PKR) | B15: =SUMIFS('Daily Summary'!$G$5:$G$404,'Daily Summary'!$A$5:$A$404,">="&$B$4,'Daily Summary'!$A$5:$A$404,"<="&$B$5) -> 339374.14
A16: Commission (PKR) | B16: =SUMIFS('Daily Summary'!$H$5:$H$404,'Daily Summary'!$A$5:$A$404,">="&$B$4,'Daily Summary'!$A$5:$A$404,"<="&$B$5) -> 129301.35
A17: SST (PKR) | B17: =SUMIFS('Daily Summary'!$I$5:$I$404,'Daily Summary'!$A$5:$A$404,">="&$B$4,'Daily Summary'!$A$5:$A$404,"<="&$B$5) -> 16809.176
A18: Total Charges (PKR) | B18: =SUMIFS('Daily Summary'!$J$5:$J$404,'Daily Summary'!$A$5:$A$404,">="&$B$4,'Daily Summary'!$A$5:$A$404,"<="&$B$5) -> 146110.53
A19: Net P&L (PKR) | B19: =SUMIFS('Daily Summary'!$K$5:$K$404,'Daily Summary'!$A$5:$A$404,">="&$B$4,'Daily Summary'!$A$5:$A$404,"<="&$B$5) -> 193263.61
A20: Return on Buy | B20: =IF($B$13=0,"",$B$19/$B$13) -> 0.00047928714
A22: Date-by-Date Breakdown
A23: Date | B23: Buy Qty | C23: Sell Qty | D23: Net Qty | E23: Buy Value (PKR) | F23: Sell Value (PKR) | G23: Gross P&L (PKR) | H23: Commission (PKR) | I23: SST (PKR) | J23: Total Charges (PKR) | K23: Net P&L (PKR) | L23: Return on Buy
A24: ='Daily Summary'!A5 -> 46251 | B24: ='Daily Summary'!B5 -> 70500 | C24: ='Daily Summary'!C5 -> 70500 | D24: ='Daily Summary'!D5 -> 0 | E24: ='Daily Summary'!E5 -> 18267720 | F24: ='Daily Summary'!F5 -> 18287930 | G24: ='Daily Summary'!G5 -> 20210 | H24: ='Daily Summary'!H5 -> 5943.5773 | ... L24: ='Daily Summary'!L5 -> 0.00073866677
A25: ='Daily Summary'!A6 -> 46252 | B25: ='Daily Summary'!B6 -> 125640 | C25: ='Daily Summary'!C6 -> 125640 | D25: ='Daily Summary'!D6 -> 0 | E25: ='Daily Summary'!E6 -> 21984905 | F25: ='Daily Summary'!F6 -> 22001335 | G25: ='Daily Summary'!G6 -> 16430 | H25: ='Daily Summary'!H6 -> 6920.3714 | ... L25: ='Daily Summary'!L6 -> 0.00039163146
A26: ='Daily Summary'!A7 -> 46253 | B26: ='Daily Summary'!B7 -> 96000 | C26: ='Daily Summary'!C7 -> 96000 | D26: ='Daily Summary'!D7 -> 0 | E26: ='Daily Summary'!E7 -> 12039745 | F26: ='Daily Summary'!F7 -> 12062720 | G26: ='Daily Summary'!G7 -> 22975 | H26: ='Daily Summary'!H7 -> 3851.2528 | ... L26: ='Daily Summary'!L7 -> 0.0015468006
A27: ='Daily Summary'!A8 -> 46254 | B27: ='Daily Summary'!B8 -> 63500 | C27: ='Daily Summary'!C8 -> 63500 | D27: ='Daily Summary'!D8 -> 0 | E27: ='Daily Summary'!E8 -> 10062968 | F27: ='Daily Summary'!F8 -> 10084865 | G27: ='Daily Summary'!G8 -> 21896.51 | H27: ='Daily Summary'!H8 -> 3277.581 | ... L27: ='Daily Summary'!L8 -> 0.0018079004
A28: ='Daily Summary'!A9 -> 46255 | B28: ='Daily Summary'!B9 -> 45357 | C28: ='Daily Summary'!C9 -> 45357 | D28: ='Daily Summary'!D9 -> 0 | E28: ='Daily Summary'!E9 -> 8763520 | F28: ='Daily Summary'!F9 -> 8772484.3 | G28: ='Daily Summary'!G9 -> 8964.29 | H28: ='Daily Summary'!H9 -> 2851.0574 | ... L28: ='Daily Summary'!L9 -> 0.00065528408
A29: ='Daily Summary'!A10 -> 46258 | B29: ='Daily Summary'!B10 -> 84004 | C29: ='Daily Summary'!C10 -> 84004 | D29: ='Daily Summary'!D10 -> 0 | E29: ='Daily Summary'!E10 -> 13130113 | F29: ='Daily Summary'!F10 -> 13155567 | G29: ='Daily Summary'!G10 -> 25454.29 | H29: ='Daily Summary'!H10 -> 4275.5592 | ... L29: ='Daily Summary'!L10 -> 0.0015706574
A30: ='Daily Summary'!A11 -> 46261 | B30: ='Daily Summary'!B11 -> 26500 | C30: ='Daily Summary'!C11 -> 26500 | D30: ='Daily Summary'!D11 -> 0 | E30: ='Daily Summary'!E11 -> 2407645 | F30: ='Daily Summary'!F11 -> 2404525 | G30: ='Daily Summary'!G11 -> -3120 | H30: ='Daily Summary'!H11 -> 781.47063 | ... L30: ='Daily Summary'!L11 -> -0.0016626462
A31: ='Daily Summary'!A12 -> 46265 | B31: ='Daily Summary'!B12 -> 51500 | C31: ='Daily Summary'!C12 -> 51500 | D31: ='Daily Summary'!D12 -> 0 | E31: ='Daily Summary'!E12 -> 18280837 | F31: ='Daily Summary'!F12 -> 18292560 | G31: ='Daily Summary'!G12 -> 11723.11 | H31: ='Daily Summary'!H12 -> 5945.082 | ... L31: ='Daily Summary'!L12 -> 0.00027379312
A32: ='Daily Summary'!A13 -> 46266 | B32: ='Daily Summary'!B13 -> 40920 | C32: ='Daily Summary'!C13 -> 40920 | D32: ='Daily Summary'!D13 -> 0 | E32: ='Daily Summary'!E13 -> 13686449 | F32: ='Daily Summary'!F13 -> 13711864 | G32: ='Daily Summary'!G13 -> 25415.3 | H32: ='Daily Summary'!H13 -> 4456.3559 | ... L32: ='Daily Summary'!L13 -> 0.0014890362
A33: ='Daily Summary'!A14 -> 46267 | B33: ='Daily Summary'!B14 -> 115000 | C33: ='Daily Summary'!C14 -> 115000 | D33: ='Daily Summary'!D14 -> 0 | E33: ='Daily Summary'!E14 -> 14853375 | F33: ='Daily Summary'!F14 -> 14863825 | G33: ='Daily Summary'!G14 -> 10450.36 | H33: ='Daily Summary'!H14 -> 4830.7432 | ... L33: ='Daily Summary'!L14 -> 0.00033605966
A34: ='Daily Summary'!A15 -> 46268 | B34: ='Daily Summary'!B15 -> 85000 | C34: ='Daily Summary'!C15 -> 85000 | D34: ='Daily Summary'!D15 -> 0 | E34: ='Daily Summary'!E15 -> 15859132 | F34: ='Daily Summary'!F15 -> 15867402 | G34: ='Daily Summary'!G15 -> 8269.59 | H34: ='Daily Summary'!H15 -> 5156.9056 | ... L34: ='Daily Summary'!L15 -> 0.00015399876
A35: ='Daily Summary'!A16 -> 46269 | B35: ='Daily Summary'!B16 -> 139200 | C35: ='Daily Summary'!C16 -> 139200 | D35: ='Daily Summary'!D16 -> 0 | E35: ='Daily Summary'!E16 -> 22870427 | F35: ='Daily Summary'!F16 -> 22877215 | G35: ='Daily Summary'!G16 -> 6788.43 | H35: ='Daily Summary'!H16 -> 7435.0949 | ... L35: ='Daily Summary'!L16 -> -7.0537697e-05
... A59: ='Daily Summary'!A40 -> 46311 | B59: ='Daily Summary'!B40 -> 22500 | C59: ='Daily Summary'!C40 -> 22500 | D59: ='Daily Summary'!D40 -> 0 | E59: ='Daily Summary'!E40 -> 4845060 | F59: ='Daily Summary'!F40 -> 4855610 | G59: ='Daily Summary'!G40 -> 10550 | H59: ='Daily Summary'!H40 -> 1578.0732 | ... L59: ='Daily Summary'!L40 -> 0.0018094259
A60: TOTAL | B60: =SUM(B24:B59) -> 2612821 | C60: =SUM(C24:C59) -> 2612821 | D60: =$B60-$C60 -> 0 | E60: =SUM(E24:E59) -> 4.0323137e+08 | F60: =SUM(F24:F59) -> 4.0357074e+08 | G60: =SUM(G24:G59) -> 339374.14 | H60: =SUM(H24:H59) -> 129301.35 | I60: =SUM(I24:I59) -> 16809.176 | J60: =SUM(J24:J59) -> 146110.53 | K60: =SUM(K24:K59) -> 193263.61 | L60: =IF($E60=0,"",$K60/$E60) -> 0.00047928714

Sheet Monthly Summary
A1: Monthly Summary — Month-Wise Performance
A2: One row per calendar month with trading data, oldest → newest. Live SUMIFS over the Daily Summary.
A4: Month | B4: Buy Qty | C4: Buy Value (PKR) | D4: Avg Buy Price | E4: Sell Qty | F4: Sell Value (PKR) | G4: Avg Sell Price | H4: Price Diff (Sell−Buy) | I4: Net Qty | J4: Gross P&L (PKR) | K4: Commission Rate (Slab) | L4: Commission (PKR) | M4: SST 13% (PKR) | N4: Total Charges (PKR) | O4: Net P&L (PKR) | P4: Return on Buy
A5: 46235 | B5: =SUMIFS('Daily Summary'!$B$5:$B$404,'Daily Summary'!$A$5:$A$404,">="&$A5,'Daily Summary'!$A$5:$A$404,"<"&DATE(YEAR($A5),MONTH($A5)+1,1)) -> 563001 | C5: =SUMIFS('Daily Summary'!$E$5:$E$404,'Daily Summary'!$A$5:$A$404,">="&$A5,'Daily Summary'!$A$5:$A$404,"<"&DATE(YEAR($A5),MONTH($A5)+1,1)) -> 1.0493745e+08 | D5: =IF($B5=0,"",$C5/$B5) -> 186.38946 | E5: =SUMIFS('Daily Summary'!$C$5:$C$404,'Daily Summary'!$A$5:$A$404,">="&$A5,'Daily Summary'!$A$5:$A$404,"<"&DATE(YEAR($A5),MONTH($A5)+1,1)) -> 563001 | F5: =SUMIFS('Daily Summary'!$F$5:$F$404,'Daily Summary'!$A$5:$A$404,">="&$A5,'Daily Summary'!$A$5:$A$404,"<"&DATE(YEAR($A5),MONTH($A5)+1,1)) -> 1.0506199e+08 | G5: =IF($E5=0,"",$F5/$E5) -> 186.61066 | H5: =IF(OR($B5=0,$E5=0),"N/A",$G5-$D5) -> 0.22119534 | I5: =$B5-$E5 -> 0 | J5: =SUMIFS('Daily Summary'!$G$5:$G$404,'Daily Summary'!$A$5:$A$404,">="&$A5,'Daily Summary'!$A$5:$A$404,"<"&DATE(YEAR($A5),MONTH($A5)+1,1)) -> 124533.2 | K5: =IF($E5=0,"—",IF($G5>=Comm_Slab2_Start,"0.0325% of sell value","0.0175 paisa per share")) -> 0.0325% of sell value | L5: =SUMIFS('Daily Summary'!$H$5:$H$404,'Daily Summary'!$A$5:$A$404,">="&$A5,'Daily Summary'!$A$5:$A$404,"<"&DATE(YEAR($A5),MONTH($A5)+1,1)) -> 33845.952 | M5: =SUMIFS('Daily Summary'!$I$5:$I$404,'Daily Summary'!$A$5:$A$404,">="&$A5,'Daily Summary'!$A$5:$A$404,"<"&DATE(YEAR($A5),MONTH($A5)+1,1)) -> 4399.9737 | N5: =$L5+$M5 -> 38245.925 | O5: =SUMIFS('Daily Summary'!$K$5:$K$404,'Daily Summary'!$A$5:$A$404,">="&$A5,'Daily Summary'!$A$5:$A$404,"<"&DATE(YEAR($A5),MONTH($A5)+1,1)) -> 86287.275 | P5: =IF($C5=0,"N/A",$O5/$C5) -> 0.00082227339
A6: 46266 | B6: =SUMIFS('Daily Summary'!$B$5:$B$404,'Daily Summary'!$A$5:$A$404,">="&$A6,'Daily Summary'!$A$5:$A$404,"<"&DATE(YEAR($A6),MONTH($A6)+1,1)) -> 1235826 | C6: =SUMIFS('Daily Summary'!$E$5:$E$404,'Daily Summary'!$A$5:$A$404,">="&$A6,'Daily Summary'!$A$5:$A$404,"<"&DATE(YEAR($A6),MONTH($A6)+1,1)) -> 1.8611513e+08 | D6: =IF($B6=0,"",$C6/$B6) -> 150.59979 | E6: =SUMIFS('Daily Summary'!$C$5:$C$404,'Daily Summary'!$A$5:$A$404,">="&$A6,'Daily Summary'!$A$5:$A$404,"<"&DATE(YEAR($A6),MONTH($A6)+1,1)) -> 1235826 | F6: =SUMIFS('Daily Summary'!$F$5:$F$404,'Daily Summary'!$A$5:$A$404,">="&$A6,'Daily Summary'!$A$5:$A$404,"<"&DATE(YEAR($A6),MONTH($A6)+1,1)) -> 1.862503e+08 | G6: =IF($E6=0,"",$F6/$E6) -> 150.70916 | H6: =IF(OR($B6=0,$E6=0),"N/A",$G6-$D6) -> 0.10937488 | I6: =$B6-$E6 -> 0 | J6: =SUMIFS('Daily Summary'!$G$5:$G$404,'Daily Summary'!$A$5:$A$404,">="&$A6,'Daily Summary'!$A$5:$A$404,"<"&DATE(YEAR($A6),MONTH($A6)+1,1)) -> 135168.32 | K6: =IF($E6=0,"—",IF($G6>=Comm_Slab2_Start,"0.0325% of sell value","0.0175 paisa per share")) -> 0.0325% of sell value | L6: =SUMIFS('Daily Summary'!$H$5:$H$404,'Daily Summary'!$A$5:$A$404,">="&$A6,'Daily Summary'!$A$5:$A$404,"<"&DATE(YEAR($A6),MONTH($A6)+1,1)) -> 60161.61 | M6: =SUMIFS('Daily Summary'!$I$5:$I$404,'Daily Summary'!$A$5:$A$404,">="&$A6,'Daily Summary'!$A$5:$A$404,"<"&DATE(YEAR($A6),MONTH($A6)+1,1)) -> 7821.0093 | N6: =$L6+$M6 -> 67982.62 | O6: =SUMIFS('Daily Summary'!$K$5:$K$404,'Daily Summary'!$A$5:$A$404,">="&$A6,'Daily Summary'!$A$5:$A$404,"<"&DATE(YEAR($A6),MONTH($A6)+1,1)) -> 67185.7 | P6: =IF($C6=0,"N/A",$O6/$C6) -> 0.00036098999
A7: 46296 | B7: =SUMIFS('Daily Summary'!$B$5:$B$404,'Daily Summary'!$A$5:$A$404,">="&$A7,'Daily Summary'!$A$5:$A$404,"<"&DATE(YEAR($A7),MONTH($A7)+1,1)) -> 813994 | C7: =SUMIFS('Daily Summary'!$E$5:$E$404,'Daily Summary'!$A$5:$A$404,">="&$A7,'Daily Summary'!$A$5:$A$404,"<"&DATE(YEAR($A7),MONTH($A7)+1,1)) -> 1.1217878e+08 | D7: =IF($B7=0,"",$C7/$B7) -> 137.81279 | E7: =SUMIFS('Daily Summary'!$C$5:$C$404,'Daily Summary'!$A$5:$A$404,">="&$A7,'Daily Summary'!$A$5:$A$404,"<"&DATE(YEAR($A7),MONTH($A7)+1,1)) -> 813994 | F7: =SUMIFS('Daily Summary'!$F$5:$F$404,'Daily Summary'!$A$5:$A$404,">="&$A7,'Daily Summary'!$A$5:$A$404,"<"&DATE(YEAR($A7),MONTH($A7)+1,1)) -> 1.1225846e+08 | G7: =IF($E7=0,"",$F7/$E7) -> 137.91067 | H7: =IF(OR($B7=0,$E7=0),"N/A",$G7-$D7) -> 0.097878633 | I7: =$B7-$E7 -> 0 | J7: =SUMIFS('Daily Summary'!$G$5:$G$404,'Daily Summary'!$A$5:$A$404,">="&$A7,'Daily Summary'!$A$5:$A$404,"<"&DATE(YEAR($A7),MONTH($A7)+1,1)) -> 79672.62 | K7: =IF($E7=0,"—",IF($G7>=Comm_Slab2_Start,"0.0325% of sell value","0.0175 paisa per share")) -> 0.0325% of sell value | L7: =SUMIFS('Daily Summary'!$H$5:$H$404,'Daily Summary'!$A$5:$A$404,">="&$A7,'Daily Summary'!$A$5:$A$404,"<"&DATE(YEAR($A7),MONTH($A7)+1,1)) -> 35293.791 | M7: =SUMIFS('Daily Summary'!$I$5:$I$404,'Daily Summary'!$A$5:$A$404,">="&$A7,'Daily Summary'!$A$5:$A$404,"<"&DATE(YEAR($A7),MONTH($A7)+1,1)) -> 4588.1929 | N7: =$L7+$M7 -> 39881.984 | O7: =SUMIFS('Daily Summary'!$K$5:$K$404,'Daily Summary'!$A$5:$A$404,">="&$A7,'Daily Summary'!$A$5:$A$404,"<"&DATE(YEAR($A7),MONTH($A7)+1,1)) -> 39790.636 | P7: =IF($C7=0,"N/A",$O7/$C7) -> 0.00035470732
A8: TOTAL | B8: =SUM(B5:B7) -> 2612821 | C8: =SUM(C5:C7) -> 4.0323137e+08 | D8: =IF($B8=0,"",$C8/$B8) -> 154.32797 | E8: =SUM(E5:E7) -> 2612821 | F8: =SUM(F5:F7) -> 4.0357074e+08 | G8: =IF($E8=0,"",$F8/$E8) -> 154.45786 | H8: =IF(OR($B8=0,$E8=0),"N/A",$G8-$D8) -> 0.12988802 | I8: =$B8-$E8 -> 0 | J8: =SUM(J5:J7) -> 339374.14 | L8: =SUM(L5:L7) -> 129301.35 | M8: =SUM(M5:M7) -> 16809.176 | N8: =$L8+$M8 -> 146110.53 | O8: =SUM(O5:O7) -> 193263.61 | P8: =IF($C8=0,"N/A",$O8/$C8) -> 0.00047928714
A10: Note: all figures accumulate the underlying execution history for the whole period (weighted averages from totals; Return on Buy = Net P&L ÷ Buy Value, never averaged). Commission is accumulated per execution; the slab label reflects the period's weighted-average sell rate.

Sheet Yearly Summary
A1: Yearly Summary — Year-Wise Performance
A2: One row per calendar year with trading data, oldest → newest. Live SUMIFS over the Daily Summary.
A4: Year | B4: Buy Qty | C4: Buy Value (PKR) | D4: Avg Buy Price | E4: Sell Qty | F4: Sell Value (PKR) | G4: Avg Sell Price | H4: Price Diff (Sell−Buy) | I4: Net Qty | J4: Gross P&L (PKR) | K4: Commission Rate (Slab) | L4: Commission (PKR) | M4: SST 13% (PKR) | N4: Total Charges (PKR) | O4: Net P&L (PKR) | P4: Return on Buy
A5: 2026 | B5: =SUMIFS('Daily Summary'!$B$5:$B$404,'Daily Summary'!$A$5:$A$404,">="&$A5,'Daily Summary'!$A$5:$A$404,"<"&DATE($A5+1,1,1)) -> 2612821 | C5: =SUMIFS('Daily Summary'!$E$5:$E$404,'Daily Summary'!$A$5:$A$404,">="&$A5,'Daily Summary'!$A$5:$A$404,"<"&DATE($A5+1,1,1)) -> 4.0323137e+08 | D5: =IF($B5=0,"",$C5/$B5) -> 154.32797 | E5: =SUMIFS('Daily Summary'!$C$5:$C$404,'Daily Summary'!$A$5:$A$404,">="&$A5,'Daily Summary'!$A$5:$A$404,"<"&DATE($A5+1,1,1)) -> 2612821 | F5: =SUMIFS('Daily Summary'!$F$5:$F$404,'Daily Summary'!$A$5:$A$404,">="&$A5,'Daily Summary'!$A$5:$A$404,"<"&DATE($A5+1,1,1)) -> 4.0357074e+08 | G5: =IF($E5=0,"",$F5/$E5) -> 154.45786 | H5: =IF(OR($B5=0,$E5=0),"N/A",$G5-$D5) -> 0.12988802 | I5: =$B5-$E5 -> 0 | J5: =SUMIFS('Daily Summary'!$G$5:$G$404,'Daily Summary'!$A$5:$A$404,">="&$A5,'Daily Summary'!$A$5:$A$404,"<"&DATE($A5+1,1,1)) -> 339374.14 | K5: =IF($E5=0,"—",IF($G5>=Comm_Slab2_Start,"0.0325% of sell value","0.0175 paisa per share")) -> 0.0325% of sell value | L5: =SUMIFS('Daily Summary'!$H$5:$H$404,'Daily Summary'!$A$5:$A$404,">="&$A5,'Daily Summary'!$A$5:$A$404,"<"&DATE($A5+1,1,1)) -> 129301.35 | M5: =SUMIFS('Daily Summary'!$I$5:$I$404,'Daily Summary'!$A$5:$A$404,">="&$A5,'Daily Summary'!$A$5:$A$404,"<"&DATE($A5+1,1,1)) -> 16809.176 | N5: =$L5+$M5 -> 146110.53 | O5: =SUMIFS('Daily Summary'!$K$5:$K$404,'Daily Summary'!$A$5:$A$404,">="&$A5,'Daily Summary'!$A$5:$A$404,"<"&DATE($A5+1,1,1)) -> 193263.61 | P5: =IF($C5=0,"N/A",$O5/$C5) -> 0.00047928714
A6: TOTAL | B6: =SUM(B5) -> 2612821 | C6: =SUM(C5) -> 4.0323137e+08 | D6: =IF($B6=0,"",$C6/$B6) -> 154.32797 | E6: =SUM(E5) -> 2612821 | F6: =SUM(F5) -> 4.0357074e+08 | G6: =IF($E6=0,"",$F6/$E6) -> 154.45786 | H6: =IF(OR($B6=0,$E6=0),"N/A",$G6-$D6) -> 0.12988802 | I6: =$B6-$E6 -> 0 | J6: =SUM(J5) -> 339374.14 | L6: =SUM(L5) -> 129301.35 | M6: =SUM(M5) -> 16809.176 | N6: =$L6+$M6 -> 146110.53 | O6: =SUM(O5) -> 193263.61 | P6: =IF($C6=0,"N/A",$O6/$C6) -> 0.00047928714
A8: Note: all figures accumulate the underlying execution history for the whole period (weighted averages from totals; Return on Buy = Net P&L ÷ Buy Value, never averaged). Commission is accumulated per execution; the slab label reflects the period's weighted-average sell rate.

Sheet Symbol Performance
A1: Symbol Performance — All Trading Dates
A2: Aggregated across the full imported history (live SUMIF over the Daily Trade Summary), sorted by Net P&L.
A4: Symbol | B4: Buy Qty | C4: Sell Qty | D4: Buy Value (PKR) | E4: Sell Value (PKR) | F4: Gross P&L (PKR) | G4: Commission (PKR) | H4: SST (PKR) | I4: Net P&L (PKR) | J4: Return on Buy
A5: PRL-AUG | B5: =SUMIF('Daily Trade Summary'!$A:$A,$A5,'Daily Trade Summary'!$B:$B) -> 212500 | C5: =SUMIF('Daily Trade Summary'!$A:$A,$A5,'Daily Trade Summary'!$E:$E) -> 212500 | D5: =SUMIF('Daily Trade Summary'!$A:$A,$A5,'Daily Trade Summary'!$C:$C) -> 17760910 | E5: =SUMIF('Daily Trade Summary'!$A:$A,$A5,'Daily Trade Summary'!$F:$F) -> 17805100 | F5: =$E5-$D5 -> 44190 | G5: =SUMIF('Daily Trade Summary'!$A:$A,$A5,'Daily Trade Summary'!$L:$L) -> 5786.6575 | H5: =$G5*SST_Rate -> 752.26548 | I5: =$F5-$G5-$H5 -> 37651.077 | J5: =IF($D5=0,"N/A",$I5/$D5) -> 0.0021198845 | K5: ◄ Best performer
A6: PRL-SEP | B6: =SUMIF('Daily Trade Summary'!$A:$A,$A6,'Daily Trade Summary'!$B:$B) -> 494000 | C6: =SUMIF('Daily Trade Summary'!$A:$A,$A6,'Daily Trade Summary'!$E:$E) -> 494000 | D6: =SUMIF('Daily Trade Summary'!$A:$A,$A6,'Daily Trade Summary'!$C:$C) -> 47581770 | E6: =SUMIF('Daily Trade Summary'!$A:$A,$A6,'Daily Trade Summary'!$F:$F) -> 47630070 | F6: =$E6-$D6 -> 48300 | G6: =SUMIF('Daily Trade Summary'!$A:$A,$A6,'Daily Trade Summary'!$L:$L) -> 15479.773 | H6: =$G6*SST_Rate -> 2012.3705 | I6: =$F6-$G6-$H6 -> 30807.857 | J6: =IF($D6=0,"N/A",$I6/$D6) -> 0.00064747185
A7: PRL | B7: =SUMIF('Daily Trade Summary'!$A:$A,$A7,'Daily Trade Summary'!$B:$B) -> 187050 | C7: =SUMIF('Daily Trade Summary'!$A:$A,$A7,'Daily Trade Summary'!$E:$E) -> 187050 | D7: =SUMIF('Daily Trade Summary'!$A:$A,$A7,'Daily Trade Summary'!$C:$C) -> 17706341 | E7: =SUMIF('Daily Trade Summary'!$A:$A,$A7,'Daily Trade Summary'!$F:$F) -> 17737430 | F7: =$E7-$D7 -> 31088.98 | G7: =SUMIF('Daily Trade Summary'!$A:$A,$A7,'Daily Trade Summary'!$L:$L) -> 5764.6647 | H7: =$G7*SST_Rate -> 749.40641 | I7: =$F7-$G7-$H7 -> 24574.909 | J7: =IF($D7=0,"N/A",$I7/$D7) -> 0.0013879157
A8: NRL-AUG | B8: =SUMIF('Daily Trade Summary'!$A:$A,$A8,'Daily Trade Summary'!$B:$B) -> 31000 | C8: =SUMIF('Daily Trade Summary'!$A:$A,$A8,'Daily Trade Summary'!$E:$E) -> 31000 | D8: =SUMIF('Daily Trade Summary'!$A:$A,$A8,'Daily Trade Summary'!$C:$C) -> 16071720 | E8: =SUMIF('Daily Trade Summary'!$A:$A,$A8,'Daily Trade Summary'!$F:$F) -> 16091315 | F8: =$E8-$D8 -> 19595 | G8: =SUMIF('Daily Trade Summary'!$A:$A,$A8,'Daily Trade Summary'!$L:$L) -> 5229.6774 | H8: =$G8*SST_Rate -> 679.85806 | I8: =$F8-$G8-$H8 -> 13685.465 | J8: =IF($D8=0,"N/A",$I8/$D8) -> 0.00085152458
A9: PPL-AUG | B9: =SUMIF('Daily Trade Summary'!$A:$A,$A9,'Daily Trade Summary'!$B:$B) -> 37000 | C9: =SUMIF('Daily Trade Summary'!$A:$A,$A9,'Daily Trade Summary'!$E:$E) -> 37000 | D9: =SUMIF('Daily Trade Summary'!$A:$A,$A9,'Daily Trade Summary'!$C:$C) -> 8881420 | E9: =SUMIF('Daily Trade Summary'!$A:$A,$A9,'Daily Trade Summary'!$F:$F) -> 8898330 | F9: =$E9-$D9 -> 16910 | G9: =SUMIF('Daily Trade Summary'!$A:$A,$A9,'Daily Trade Summary'!$L:$L) -> 2891.9572 | H9: =$G9*SST_Rate -> 375.95444 | I9: =$F9-$G9-$H9 -> 13642.088 | J9: =IF($D9=0,"N/A",$I9/$D9) -> 0.0015360256
A10: NRL-SEP | B10: =SUMIF('Daily Trade Summary'!$A:$A,$A10,'Daily Trade Summary'!$B:$B) -> 88500 | C10: =SUMIF('Daily Trade Summary'!$A:$A,$A10,'Daily Trade Summary'!$E:$E) -> 88500 | D10: =SUMIF('Daily Trade Summary'!$A:$A,$A10,'Daily Trade Summary'!$C:$C) -> 46865190 | E10: =SUMIF('Daily Trade Summary'!$A:$A,$A10,'Daily Trade Summary'!$F:$F) -> 46895670 | F10: =$E10-$D10 -> 30480 | G10: =SUMIF('Daily Trade Summary'!$A:$A,$A10,'Daily Trade Summary'!$L:$L) -> 15241.093 | H10: =$G10*SST_Rate -> 1981.3421 | I10: =$F10-$G10-$H10 -> 13257.565 | J10: =IF($D10=0,"N/A",$I10/$D10) -> 0.00028288726
A11: PRL-OCT | B11: =SUMIF('Daily Trade Summary'!$A:$A,$A11,'Daily Trade Summary'!$B:$B) -> 658500 | C11: =SUMIF('Daily Trade Summary'!$A:$A,$A11,'Daily Trade Summary'!$E:$E) -> 658500 | D11: =SUMIF('Daily Trade Summary'!$A:$A,$A11,'Daily Trade Summary'!$C:$C) -> 62249075 | E11: =SUMIF('Daily Trade Summary'!$A:$A,$A11,'Daily Trade Summary'!$F:$F) -> 62282360 | F11: =$E11-$D11 -> 33285 | G11: =SUMIF('Daily Trade Summary'!$A:$A,$A11,'Daily Trade Summary'!$L:$L) -> 20241.767 | H11: =$G11*SST_Rate -> 2631.4297 | I11: =$F11-$G11-$H11 -> 10411.803 | J11: =IF($D11=0,"N/A",$I11/$D11) -> 0.00016726037
A12: NRL-OCT | B12: =SUMIF('Daily Trade Summary'!$A:$A,$A12,'Daily Trade Summary'!$B:$B) -> 56500 | C12: =SUMIF('Daily Trade Summary'!$A:$A,$A12,'Daily Trade Summary'!$E:$E) -> 56500 | D12: =SUMIF('Daily Trade Summary'!$A:$A,$A12,'Daily Trade Summary'!$C:$C) -> 34719095 | E12: =SUMIF('Daily Trade Summary'!$A:$A,$A12,'Daily Trade Summary'!$F:$F) -> 34741665 | F12: =$E12-$D12 -> 22570 | G12: =SUMIF('Daily Trade Summary'!$A:$A,$A12,'Daily Trade Summary'!$L:$L) -> 11291.041 | H12: =$G12*SST_Rate -> 1467.8353 | I12: =$F12-$G12-$H12 -> 9811.1235 | J12: =IF($D12=0,"N/A",$I12/$D12) -> 0.00028258581
A13: FCCL-OCTB | B13: =SUMIF('Daily Trade Summary'!$A:$A,$A13,'Daily Trade Summary'!$B:$B) -> 30000 | C13: =SUMIF('Daily Trade Summary'!$A:$A,$A13,'Daily Trade Summary'!$E:$E) -> 30000 | D13: =SUMIF('Daily Trade Summary'!$A:$A,$A13,'Daily Trade Summary'!$C:$C) -> 1581000 | E13: =SUMIF('Daily Trade Summary'!$A:$A,$A13,'Daily Trade Summary'!$F:$F) -> 1585695 | F13: =$E13-$D13 -> 4695 | G13: =SUMIF('Daily Trade Summary'!$A:$A,$A13,'Daily Trade Summary'!$L:$L) -> 179.65 | H13: =$G13*SST_Rate -> 23.3545 | I13: =$F13-$G13-$H13 -> 4491.9955 | J13: =IF($D13=0,"N/A",$I13/$D13) -> 0.0028412369
A14: PTC-OCT | B14: =SUMIF('Daily Trade Summary'!$A:$A,$A14,'Daily Trade Summary'!$B:$B) -> 50000 | C14: =SUMIF('Daily Trade Summary'!$A:$A,$A14,'Daily Trade Summary'!$E:$E) -> 50000 | D14: =SUMIF('Daily Trade Summary'!$A:$A,$A14,'Daily Trade Summary'!$C:$C) -> 2751570 | E14: =SUMIF('Daily Trade Summary'!$A:$A,$A14,'Daily Trade Summary'!$F:$F) -> 2756225 | F14: =$E14-$D14 -> 4655 | G14: =SUMIF('Daily Trade Summary'!$A:$A,$A14,'Daily Trade Summary'!$L:$L) -> 207.85 | H14: =$G14*SST_Rate -> 27.0205 | I14: =$F14-$G14-$H14 -> 4420.1295 | J14: =IF($D14=0,"N/A",$I14/$D14) -> 0.0016064027
A15: PPL-OCTB | B15: =SUMIF('Daily Trade Summary'!$A:$A,$A15,'Daily Trade Summary'!$B:$B) -> 5000 | C15: =SUMIF('Daily Trade Summary'!$A:$A,$A15,'Daily Trade Summary'!$E:$E) -> 5000 | D15: =SUMIF('Daily Trade Summary'!$A:$A,$A15,'Daily Trade Summary'!$C:$C) -> 1065500 | E15: =SUMIF('Daily Trade Summary'!$A:$A,$A15,'Daily Trade Summary'!$F:$F) -> 1070000 | F15: =$E15-$D15 -> 4500 | G15: =SUMIF('Daily Trade Summary'!$A:$A,$A15,'Daily Trade Summary'!$L:$L) -> 347.75 | H15: =$G15*SST_Rate -> 45.2075 | I15: =$F15-$G15-$H15 -> 4107.0425 | J15: =IF($D15=0,"N/A",$I15/$D15) -> 0.0038545683
A16: PSO-OCT | B16: =SUMIF('Daily Trade Summary'!$A:$A,$A16,'Daily Trade Summary'!$B:$B) -> 12500 | C16: =SUMIF('Daily Trade Summary'!$A:$A,$A16,'Daily Trade Summary'!$E:$E) -> 12500 | D16: =SUMIF('Daily Trade Summary'!$A:$A,$A16,'Daily Trade Summary'!$C:$C) -> 4513315 | E16: =SUMIF('Daily Trade Summary'!$A:$A,$A16,'Daily Trade Summary'!$F:$F) -> 4518635 | F16: =$E16-$D16 -> 5320 | G16: =SUMIF('Daily Trade Summary'!$A:$A,$A16,'Daily Trade Summary'!$L:$L) -> 1468.5564 | H16: =$G16*SST_Rate -> 190.91233 | I16: =$F16-$G16-$H16 -> 3660.5313 | J16: =IF($D16=0,"N/A",$I16/$D16) -> 0.00081105159
A17: DGKC-SEP | B17: =SUMIF('Daily Trade Summary'!$A:$A,$A17,'Daily Trade Summary'!$B:$B) -> 26000 | C17: =SUMIF('Daily Trade Summary'!$A:$A,$A17,'Daily Trade Summary'!$E:$E) -> 26000 | D17: =SUMIF('Daily Trade Summary'!$A:$A,$A17,'Daily Trade Summary'!$C:$C) -> 5123920 | E17: =SUMIF('Daily Trade Summary'!$A:$A,$A17,'Daily Trade Summary'!$F:$F) -> 5129445 | F17: =$E17-$D17 -> 5525 | G17: =SUMIF('Daily Trade Summary'!$A:$A,$A17,'Daily Trade Summary'!$L:$L) -> 1667.0696 | H17: =$G17*SST_Rate -> 216.71905 | I17: =$F17-$G17-$H17 -> 3641.2113 | J17: =IF($D17=0,"N/A",$I17/$D17) -> 0.00071063001
... A60: GAL-SEP | B60: =SUMIF('Daily Trade Summary'!$A:$A,$A60,'Daily Trade Summary'!$B:$B) -> 3000 | C60: =SUMIF('Daily Trade Summary'!$A:$A,$A60,'Daily Trade Summary'!$E:$E) -> 3000 | D60: =SUMIF('Daily Trade Summary'!$A:$A,$A60,'Daily Trade Summary'!$C:$C) -> 1636990 | E60: =SUMIF('Daily Trade Summary'!$A:$A,$A60,'Daily Trade Summary'!$F:$F) -> 1635010 | F60: =$E60-$D60 -> -1980 | G60: =SUMIF('Daily Trade Summary'!$A:$A,$A60,'Daily Trade Summary'!$L:$L) -> 531.37825 | H60: =$G60*SST_Rate -> 69.079172 | I60: =$F60-$G60-$H60 -> -2580.4574 | J60: =IF($D60=0,"N/A",$I60/$D60) -> -0.0015763428
A61: OGDC-OCTB | B61: =SUMIF('Daily Trade Summary'!$A:$A,$A61,'Daily Trade Summary'!$B:$B) -> 12000 | C61: =SUMIF('Daily Trade Summary'!$A:$A,$A61,'Daily Trade Summary'!$E:$E) -> 12000 | D61: =SUMIF('Daily Trade Summary'!$A:$A,$A61,'Daily Trade Summary'!$C:$C) -> 3729680 | E61: =SUMIF('Daily Trade Summary'!$A:$A,$A61,'Daily Trade Summary'!$F:$F) -> 3727865 | F61: =$E61-$D61 -> -1815 | G61: =SUMIF('Daily Trade Summary'!$A:$A,$A61,'Daily Trade Summary'!$L:$L) -> 1211.5561 | H61: =$G61*SST_Rate -> 157.5023 | I61: =$F61-$G61-$H61 -> -3184.0584 | J61: =IF($D61=0,"N/A",$I61/$D61) -> -0.00085370821 | K61: ◄ Worst performer
A62: TOTAL | B62: =SUM(B5:B61) -> 2612821 | C62: =SUM(C5:C61) -> 2612821 | D62: =SUM(D5:D61) -> 4.0323137e+08 | E62: =SUM(E5:E61) -> 4.0357074e+08 | F62: =SUM(F5:F61) -> 339374.14 | G62: =SUM(G5:G61) -> 129301.35 | H62: =SUM(H5:H61) -> 16809.176 | I62: =SUM(I5:I61) -> 193263.61 | J62: =IF($D62=0,"N/A",$I62/$D62) -> 0.00047928714

Sheet Daily Trade Summary
A1: Daily Trade Summary — 17 Aug 2026 | B1: Buy Qty | C1: Buy Value (PKR) | D1: Avg Buy Price | E1: Sell Qty | F1: Sell Value (PKR) | G1: Avg Sell Price | H1: Price Diff (Sell−Buy) | I1: Net Qty | J1: Gross P&L (PKR) | K1: Commission Rate (Slab) | L1: Commission (PKR) | M1: SST 13% (PKR) | N1: Total Charges (PKR) | O1: Net P&L (PKR) | P1: Return on Buy
A2: Gross intraday buy/sell flow • commission & SST • net P&L (all values PKR) | D2: Day Results
A3: Trading Date: | B3: 46251 | D3: Total Buy Value | E3: =C21 -> 18267720
A4: Account: | B4: THM00601 (A/c 91404) | D4: Total Sell Value | E4: =F21 -> 18287930
A5: Market: | B5: FUT (futures/derivatives) | D5: Gross P&L | E5: =J21 -> 20210
A6: Trading Session: | B6: Full day 00:00–23:59 (per source log) | D6: Commission | E6: =L21 -> 5943.5773
A7: Currency: | B7: PKR | D7: SST (13%) | E7: =M21 -> 772.66504
A8: Source File: | B8: TradeLog-17-08-2026.txt | D8: Total Charges | E8: =N21 -> 6716.2423
D9: Net P&L | E9: =O21 -> 13493.758
D10: Return on Buy | E10: =P21 -> 0.00073866677
D11: Net Position (shares) | E11: =I21 -> 0
A12: Symbol-Level Summary
A13: Symbol | B13: Buy Qty | C13: Buy Value (PKR) | D13: Avg Buy Price | E13: Sell Qty | F13: Sell Value (PKR) | G13: Avg Sell Price | H13: Price Diff (Sell−Buy) | I13: Net Qty | J13: Gross P&L (PKR) | K13: Commission Rate (Slab) | L13: Commission (PKR) | M13: SST 13% (PKR) | N13: Total Charges (PKR) | O13: Net P&L (PKR) | P13: Return on Buy
A14: NML-AUG | B14: 1000 | C14: 151790 | D14: =IF($B14=0,"",$C14/$B14) -> 151.79 | E14: 1000 | F14: 151970 | G14: =IF($E14=0,"",$F14/$E14) -> 151.97 | H14: =IF(OR($B14=0,$E14=0),"N/A",$G14-$D14) -> 0.18 | I14: =$B14-$E14 -> 0 | J14: =$F14-$C14 -> 180 | K14: =IF($E14=0,"—",IF($G14>=Comm_Slab2_Start,"0.0325% of sell value","0.0175 paisa per share")) -> 0.0325% of sell value | L14: =IF($E14=0,0,IF($G14>=Comm_Slab2_Start,$F14*Comm_Slab2_Rate,$E14*Comm_Slab1_Paisa/Paisa_Per_PKR)) -> 49.39025 | M14: =$L14*SST_Rate -> 6.4207325 | N14: =$L14+$M14 -> 55.810983 | O14: =$J14-$N14 -> 124.18902 | P14: =IF($C14=0,"N/A",$O14/$C14) -> 0.00081816337
A15: NRL-AUG | B15: 7000 | C15: 3650535 | D15: =IF($B15=0,"",$C15/$B15) -> 521.505 | E15: 7000 | F15: 3658210 | G15: =IF($E15=0,"",$F15/$E15) -> 522.60143 | H15: =IF(OR($B15=0,$E15=0),"N/A",$G15-$D15) -> 1.0964286 | I15: =$B15-$E15 -> 0 | J15: =$F15-$C15 -> 7675 | K15: =IF($E15=0,"—",IF($G15>=Comm_Slab2_Start,"0.0325% of sell value","0.0175 paisa per share")) -> 0.0325% of sell value | L15: =IF($E15=0,0,IF($G15>=Comm_Slab2_Start,$F15*Comm_Slab2_Rate,$E15*Comm_Slab1_Paisa/Paisa_Per_PKR)) -> 1188.9182 | M15: =$L15*SST_Rate -> 154.55937 | N15: =$L15+$M15 -> 1343.4776 | O15: =$J15-$N15 -> 6331.5224 | P15: =IF($C15=0,"N/A",$O15/$C15) -> 0.0017344094
A16: OGDC-AUG | B16: 6500 | C16: 2113320 | D16: =IF($B16=0,"",$C16/$B16) -> 325.12615 | E16: 6500 | F16: 2111350 | G16: =IF($E16=0,"",$F16/$E16) -> 324.82308 | H16: =IF(OR($B16=0,$E16=0),"N/A",$G16-$D16) -> -0.30307692 | I16: =$B16-$E16 -> 0 | J16: =$F16-$C16 -> -1970 | K16: =IF($E16=0,"—",IF($G16>=Comm_Slab2_Start,"0.0325% of sell value","0.0175 paisa per share")) -> 0.0325% of sell value | L16: =IF($E16=0,0,IF($G16>=Comm_Slab2_Start,$F16*Comm_Slab2_Rate,$E16*Comm_Slab1_Paisa/Paisa_Per_PKR)) -> 686.18875 | M16: =$L16*SST_Rate -> 89.204538 | N16: =$L16+$M16 -> 775.39329 | O16: =$J16-$N16 -> -2745.3933 | P16: =IF($C16=0,"N/A",$O16/$C16) -> -0.0012990902
A17: PPL-AUG | B17: 5000 | C17: 1192745 | D17: =IF($B17=0,"",$C17/$B17) -> 238.549 | E17: 5000 | F17: 1190925 | G17: =IF($E17=0,"",$F17/$E17) -> 238.185 | H17: =IF(OR($B17=0,$E17=0),"N/A",$G17-$D17) -> -0.364 | I17: =$B17-$E17 -> 0 | J17: =$F17-$C17 -> -1820 | K17: =IF($E17=0,"—",IF($G17>=Comm_Slab2_Start,"0.0325% of sell value","0.0175 paisa per share")) -> 0.0325% of sell value | L17: =IF($E17=0,0,IF($G17>=Comm_Slab2_Start,$F17*Comm_Slab2_Rate,$E17*Comm_Slab1_Paisa/Paisa_Per_PKR)) -> 387.05063 | M17: =$L17*SST_Rate -> 50.316581 | N17: =$L17+$M17 -> 437.36721 | O17: =$J17-$N17 -> -2257.3672 | P17: =IF($C17=0,"N/A",$O17/$C17) -> -0.0018925816
A18: PRL-AUG | B18: 26000 | C18: 2058660 | D18: =IF($B18=0,"",$C18/$B18) -> 79.179231 | E18: 26000 | F18: 2071730 | G18: =IF($E18=0,"",$F18/$E18) -> 79.681923 | H18: =IF(OR($B18=0,$E18=0),"N/A",$G18-$D18) -> 0.50269231 | I18: =$B18-$E18 -> 0 | J18: =$F18-$C18 -> 13070 | K18: =IF($E18=0,"—",IF($G18>=Comm_Slab2_Start,"0.0325% of sell value","0.0175 paisa per share")) -> 0.0325% of sell value | L18: =IF($E18=0,0,IF($G18>=Comm_Slab2_Start,$F18*Comm_Slab2_Rate,$E18*Comm_Slab1_Paisa/Paisa_Per_PKR)) -> 673.31225 | M18: =$L18*SST_Rate -> 87.530592 | N18: =$L18+$M18 -> 760.84284 | O18: =$J18-$N18 -> 12309.157 | P18: =IF($C18=0,"N/A",$O18/$C18) -> 0.0059792084
A19: PRL-SEP | B19: 500 | C19: 42925 | D19: =IF($B19=0,"",$C19/$B19) -> 85.85 | E19: 500 | F19: 42760 | G19: =IF($E19=0,"",$F19/$E19) -> 85.52 | H19: =IF(OR($B19=0,$E19=0),"N/A",$G19-$D19) -> -0.33 | I19: =$B19-$E19 -> 0 | J19: =$F19-$C19 -> -165 | K19: =IF($E19=0,"—",IF($G19>=Comm_Slab2_Start,"0.0325% of sell value","0.0175 paisa per share")) -> 0.0325% of sell value | L19: =IF($E19=0,0,IF($G19>=Comm_Slab2_Start,$F19*Comm_Slab2_Rate,$E19*Comm_Slab1_Paisa/Paisa_Per_PKR)) -> 13.897 | M19: =$L19*SST_Rate -> 1.80661 | N19: =$L19+$M19 -> 15.70361 | O19: =$J19-$N19 -> -180.70361 | P19: =IF($C19=0,"N/A",$O19/$C19) -> -0.0042097521
A20: PSO-AUG | B20: 24500 | C20: 9057745 | D20: =IF($B20=0,"",$C20/$B20) -> 369.70388 | E20: 24500 | F20: 9060985 | G20: =IF($E20=0,"",$F20/$E20) -> 369.83612 | H20: =IF(OR($B20=0,$E20=0),"N/A",$G20-$D20) -> 0.1322449 | I20: =$B20-$E20 -> 0 | J20: =$F20-$C20 -> 3240 | K20: =IF($E20=0,"—",IF($G20>=Comm_Slab2_Start,"0.0325% of sell value","0.0175 paisa per share")) -> 0.0325% of sell value | L20: =IF($E20=0,0,IF($G20>=Comm_Slab2_Start,$F20*Comm_Slab2_Rate,$E20*Comm_Slab1_Paisa/Paisa_Per_PKR)) -> 2944.8201 | M20: =$L20*SST_Rate -> 382.82662 | N20: =$L20+$M20 -> 3327.6467 | O20: =$J20-$N20 -> -87.646741 | P20: =IF($C20=0,"N/A",$O20/$C20) -> -9.6764417e-06
A21: TOTAL | B21: =SUM(B14:B20) -> 70500 | C21: =SUM(C14:C20) -> 18267720 | D21: =IF($B21=0,"",$C21/$B21) -> 259.1166 | E21: =SUM(E14:E20) -> 70500 | F21: =SUM(F14:F20) -> 18287930 | G21: =IF($E21=0,"",$F21/$E21) -> 259.40326 | H21: =IF(OR($B21=0,$E21=0),"N/A",$G21-$D21) -> 0.28666667 | I21: =$B21-$E21 -> 0 | J21: =SUM(J14:J20) -> 20210 | L21: =SUM(L14:L20) -> 5943.5773 | M21: =SUM(M14:M20) -> 772.66504 | N21: =$L21+$M21 -> 6716.2423 | O21: =SUM(O14:O20) -> 13493.758 | P21: =IF($C21=0,"N/A",$O21/$C21) -> 0.00073866677
A24: Daily Trade Summary — 18 Aug 2026
A25: Gross intraday buy/sell flow • commission & SST • net P&L (all values PKR) | D25: Day Results
A26: Trading Date: | B26: 46252 | D26: Total Buy Value | E26: =C47 -> 21984905
A27: Account: | B27: THM00601 (A/c 91404) | D27: Total Sell Value | E27: =F47 -> 22001335
A28: Market: | B28: FUT (futures/derivatives), Reg (regular/cash market) | D28: Gross P&L | E28: =J47 -> 16430
A29: Trading Session: | B29: Full day 00:00–23:59 (per source log) | D29: Commission | E29: =L47 -> 6920.3714
A30: Currency: | B30: PKR | D30: SST (13%) | E30: =M47 -> 899.64828
A31: Source File: | B31: TradeLog-18-08-2026.txt | D31: Total Charges | E31: =N47 -> 7820.0197
D32: Net P&L | E32: =O47 -> 8609.9803
D33: Return on Buy | E33: =P47 -> 0.00039163146
D34: Net Position (shares) | E34: =I47 -> 0
A35: Symbol-Level Summary
A36: Symbol | B36: Buy Qty | C36: Buy Value (PKR) | D36: Avg Buy Price | E36: Sell Qty | F36: Sell Value (PKR) | G36: Avg Sell Price | H36: Price Diff (Sell−Buy) | I36: Net Qty | J36: Gross P&L (PKR) | K36: Commission Rate (Slab) | L36: Commission (PKR) | M36: SST 13% (PKR) | N36: Total Charges (PKR) | O36: Net P&L (PKR) | P36: Return on Buy
A37: BOP-AUG | B37: 10000 | C37: 350000 | D37: =IF($B37=0,"",$C37/$B37) -> 35 | E37: 10000 | F37: 350025 | G37: =IF($E37=0,"",$F37/$E37) -> 35.0025 | H37: =IF(OR($B37=0,$E37=0),"N/A",$G37-$D37) -> 0.0025 | I37: =$B37-$E37 -> 0 | J37: =$F37-$C37 -> 25 | K37: =IF($E37=0,"—",IF($G37>=Comm_Slab2_Start,"0.0325% of sell value","0.0175 paisa per share")) -> 0.0175 paisa per share | L37: =IF($E37=0,0,IF($G37>=Comm_Slab2_Start,$F37*Comm_Slab2_Rate,$E37*Comm_Slab1_Paisa/Paisa_Per_PKR)) -> 1.75 | M37: =$L37*SST_Rate -> 0.2275 | N37: =$L37+$M37 -> 1.9775 | O37: =$J37-$N37 -> 23.0225 | P37: =IF($C37=0,"N/A",$O37/$C37) -> 6.5778571e-05
A38: NBP-AUG | B38: 7500 | C38: 1564830 | D38: =IF($B38=0,"",$C38/$B38) -> 208.644 | E38: 7500 | F38: 1563750 | G38: =IF($E38=0,"",$F38/$E38) -> 208.5 | H38: =IF(OR($B38=0,$E38=0),"N/A",$G38-$D38) -> -0.144 | I38: =$B38-$E38 -> 0 | J38: =$F38-$C38 -> -1080 | K38: =IF($E38=0,"—",IF($G38>=Comm_Slab2_Start,"0.0325% of sell value","0.0175 paisa per share")) -> 0.0325% of sell value | L38: =IF($E38=0,0,IF($G38>=Comm_Slab2_Start,$F38*Comm_Slab2_Rate,$E38*Comm_Slab1_Paisa/Paisa_Per_PKR)) -> 508.21875 | M38: =$L38*SST_Rate -> 66.068438 | N38: =$L38+$M38 -> 574.28719 | O38: =$J38-$N38 -> -1654.2872 | P38: =IF($C38=0,"N/A",$O38/$C38) -> -0.0010571674
A39: NRL | B39: 1000 | C39: 536000 | D39: =IF($B39=0,"",$C39/$B39) -> 536 | E39: 1000 | F39: 536000 | G39: =IF($E39=0,"",$F39/$E39) -> 536 | H39: =IF(OR($B39=0,$E39=0),"N/A",$G39-$D39) -> 0 | I39: =$B39-$E39 -> 0 | J39: =$F39-$C39 -> 0 | K39: =IF($E39=0,"—",IF($G39>=Comm_Slab2_Start,"0.0325% of sell value","0.0175 paisa per share")) -> 0.0325% of sell value | L39: =IF($E39=0,0,IF($G39>=Comm_Slab2_Start,$F39*Comm_Slab2_Rate,$E39*Comm_Slab1_Paisa/Paisa_Per_PKR)) -> 174.2 | M39: =$L39*SST_Rate -> 22.646 | N39: =$L39+$M39 -> 196.846 | O39: =$J39-$N39 -> -196.846 | P39: =IF($C39=0,"N/A",$O39/$C39) -> -0.00036725
A40: NRL-AUG | B40: 13500 | C40: 7110950 | D40: =IF($B40=0,"",$C40/$B40) -> 526.73704 | E40: 13500 | F40: 7112005 | G40: =IF($E40=0,"",$F40/$E40) -> 526.81519 | H40: =IF(OR($B40=0,$E40=0),"N/A",$G40-$D40) -> 0.078148148 | I40: =$B40-$E40 -> 0 | J40: =$F40-$C40 -> 1055 | K40: =IF($E40=0,"—",IF($G40>=Comm_Slab2_Start,"0.0325% of sell value","0.0175 paisa per share")) -> 0.0325% of sell value | L40: =IF($E40=0,0,IF($G40>=Comm_Slab2_Start,$F40*Comm_Slab2_Rate,$E40*Comm_Slab1_Paisa/Paisa_Per_PKR)) -> 2311.4016 | M40: =$L40*SST_Rate -> 300.48221 | N40: =$L40+$M40 -> 2611.8838 | O40: =$J40-$N40 -> -1556.8838 | P40: =IF($C40=0,"N/A",$O40/$C40) -> -0.00021894175
A41: PPL | B41: 40 | C41: 9290 | D41: =IF($B41=0,"",$C41/$B41) -> 232.25 | E41: 40 | F41: 9320 | G41: =IF($E41=0,"",$F41/$E41) -> 233 | H41: =IF(OR($B41=0,$E41=0),"N/A",$G41-$D41) -> 0.75 | I41: =$B41-$E41 -> 0 | J41: =$F41-$C41 -> 30 | K41: =IF($E41=0,"—",IF($G41>=Comm_Slab2_Start,"0.0325% of sell value","0.0175 paisa per share")) -> 0.0325% of sell value | L41: =IF($E41=0,0,IF($G41>=Comm_Slab2_Start,$F41*Comm_Slab2_Rate,$E41*Comm_Slab1_Paisa/Paisa_Per_PKR)) -> 3.029 | M41: =$L41*SST_Rate -> 0.39377 | N41: =$L41+$M41 -> 3.42277 | O41: =$J41-$N41 -> 26.57723 | P41: =IF($C41=0,"N/A",$O41/$C41) -> 0.0028608428
A42: PPL-AUG | B42: 12000 | C42: 2862395 | D42: =IF($B42=0,"",$C42/$B42) -> 238.53292 | E42: 12000 | F42: 2866355 | G42: =IF($E42=0,"",$F42/$E42) -> 238.86292 | H42: =IF(OR($B42=0,$E42=0),"N/A",$G42-$D42) -> 0.33 | I42: =$B42-$E42 -> 0 | J42: =$F42-$C42 -> 3960 | K42: =IF($E42=0,"—",IF($G42>=Comm_Slab2_Start,"0.0325% of sell value","0.0175 paisa per share")) -> 0.0325% of sell value | L42: =IF($E42=0,0,IF($G42>=Comm_Slab2_Start,$F42*Comm_Slab2_Rate,$E42*Comm_Slab1_Paisa/Paisa_Per_PKR)) -> 931.56538 | M42: =$L42*SST_Rate -> 121.1035 | N42: =$L42+$M42 -> 1052.6689 | O42: =$J42-$N42 -> 2907.3311 | P42: =IF($C42=0,"N/A",$O42/$C42) -> 0.0010156988
A43: PRL-AUG | B43: 58500 | C43: 5047085 | D43: =IF($B43=0,"",$C43/$B43) -> 86.274957 | E43: 58500 | F43: 5059075 | G43: =IF($E43=0,"",$F43/$E43) -> 86.479915 | H43: =IF(OR($B43=0,$E43=0),"N/A",$G43-$D43) -> 0.20495726 | I43: =$B43-$E43 -> 0 | J43: =$F43-$C43 -> 11990 | K43: =IF($E43=0,"—",IF($G43>=Comm_Slab2_Start,"0.0325% of sell value","0.0175 paisa per share")) -> 0.0325% of sell value | L43: =IF($E43=0,0,IF($G43>=Comm_Slab2_Start,$F43*Comm_Slab2_Rate,$E43*Comm_Slab1_Paisa/Paisa_Per_PKR)) -> 1644.1994 | M43: =$L43*SST_Rate -> 213.74592 | N43: =$L43+$M43 -> 1857.9453 | O43: =$J43-$N43 -> 10132.055 | P43: =IF($C43=0,"N/A",$O43/$C43) -> 0.0020075063
A44: PSO | B44: 600 | C44: 231330 | D44: =IF($B44=0,"",$C44/$B44) -> 385.55 | E44: 600 | F44: 231825 | G44: =IF($E44=0,"",$F44/$E44) -> 386.375 | H44: =IF(OR($B44=0,$E44=0),"N/A",$G44-$D44) -> 0.825 | I44: =$B44-$E44 -> 0 | J44: =$F44-$C44 -> 495 | K44: =IF($E44=0,"—",IF($G44>=Comm_Slab2_Start,"0.0325% of sell value","0.0175 paisa per share")) -> 0.0325% of sell value | L44: =IF($E44=0,0,IF($G44>=Comm_Slab2_Start,$F44*Comm_Slab2_Rate,$E44*Comm_Slab1_Paisa/Paisa_Per_PKR)) -> 75.343125 | M44: =$L44*SST_Rate -> 9.7946062 | N44: =$L44+$M44 -> 85.137731 | O44: =$J44-$N44 -> 409.86227 | P44: =IF($C44=0,"N/A",$O44/$C44) -> 0.0017717644
A45: PSO-AUG | B45: 10000 | C45: 3903305 | D45: =IF($B45=0,"",$C45/$B45) -> 390.3305 | E45: 10000 | F45: 3903005 | G45: =IF($E45=0,"",$F45/$E45) -> 390.3005 | H45: =IF(OR($B45=0,$E45=0),"N/A",$G45-$D45) -> -0.03 | I45: =$B45-$E45 -> 0 | J45: =$F45-$C45 -> -300 | K45: =IF($E45=0,"—",IF($G45>=Comm_Slab2_Start,"0.0325% of sell value","0.0175 paisa per share")) -> 0.0325% of sell value | L45: =IF($E45=0,0,IF($G45>=Comm_Slab2_Start,$F45*Comm_Slab2_Rate,$E45*Comm_Slab1_Paisa/Paisa_Per_PKR)) -> 1268.4766 | M45: =$L45*SST_Rate -> 164.90196 | N45: =$L45+$M45 -> 1433.3786 | O45: =$J45-$N45 -> -1733.3786 | P45: =IF($C45=0,"N/A",$O45/$C45) -> -0.00044407972
A46: SSGC-AUG | B46: 12500 | C46: 369720 | D46: =IF($B46=0,"",$C46/$B46) -> 29.5776 | E46: 12500 | F46: 369975 | G46: =IF($E46=0,"",$F46/$E46) -> 29.598 | H46: =IF(OR($B46=0,$E46=0),"N/A",$G46-$D46) -> 0.0204 | I46: =$B46-$E46 -> 0 | J46: =$F46-$C46 -> 255 | K46: =IF($E46=0,"—",IF($G46>=Comm_Slab2_Start,"0.0325% of sell value","0.0175 paisa per share")) -> 0.0175 paisa per share | L46: =IF($E46=0,0,IF($G46>=Comm_Slab2_Start,$F46*Comm_Slab2_Rate,$E46*Comm_Slab1_Paisa/Paisa_Per_PKR)) -> 2.1875 | M46: =$L46*SST_Rate -> 0.284375 | N46: =$L46+$M46 -> 2.471875 | O46: =$J46-$N46 -> 252.52812 | P46: =IF($C46=0,"N/A",$O46/$C46) -> 0.00068302533
A47: TOTAL | B47: =SUM(B37:B46) -> 125640 | C47: =SUM(C37:C46) -> 21984905 | D47: =IF($B47=0,"",$C47/$B47) -> 174.98333 | E47: =SUM(E37:E46) -> 125640 | F47: =SUM(F37:F46) -> 22001335 | G47: =IF($E47=0,"",$F47/$E47) -> 175.1141 | H47: =IF(OR($B47=0,$E47=0),"N/A",$G47-$D47) -> 0.13077046 | I47: =$B47-$E47 -> 0 | J47: =SUM(J37:J46) -> 16430 | L47: =SUM(L37:L46) -> 6920.3714 | M47: =SUM(M37:M46) -> 899.64828 | N47: =$L47+$M47 -> 7820.0197 | O47: =SUM(O37:O46) -> 8609.9803 | P47: =IF($C47=0,"N/A",$O47/$C47) -> 0.00039163146
A50: Daily Trade Summary — 19 Aug 2026
A51: Gross intraday buy/sell flow • commission & SST • net P&L (all values PKR) | D51: Day Results
A52: Trading Date: | B52: 46253 | D52: Total Buy Value | E52: =C70 -> 12039745
A53: Account: | B53: THM00601 (A/c 91404) | D53: Total Sell Value | E53: =F70 -> 12062720
A54: Market: | B54: FUT (futures/derivatives) | D54: Gross P&L | E54: =J70 -> 22975
A55: Trading Session: | B55: Full day 00:00–23:59 (per source log) | D55: Commission | E55: =L70 -> 3851.2528
A56: Currency: | B56: PKR | D56: SST (13%) | E56: =M70 -> 500.66286
A57: Source File: | B57: TradeLog-19-08-2026.txt | D57: Total Charges | E57: =N70 -> 4351.9156
D58: Net P&L | E58: =O70 -> 18623.084
D59: Return on Buy | E59: =P70 -> 0.0015468006
D60: Net Position (shares) | E60: =I70 -> 0
A61: Symbol-Level Summary
A62: Symbol | B62: Buy Qty | C62: Buy Value (PKR) | D62: Avg Buy Price | E62: Sell Qty | F62: Sell Value (PKR) | G62: Avg Sell Price | H62: Price Diff (Sell−Buy) | I62: Net Qty | J62: Gross P&L (PKR) | K62: Commission Rate (Slab) | L62: Commission (PKR) | M62: SST 13% (PKR) | N62: Total Charges (PKR) | O62: Net P&L (PKR) | P62: Return on Buy
A63: DGKC-AUG | B63: 2500 | C63: 538725 | D63: =IF($B63=0,"",$C63/$B63) -> 215.49 | E63: 2500 | F63: 539250 | G63: =IF($E63=0,"",$F63/$E63) -> 215.7 | H63: =IF(OR($B63=0,$E63=0),"N/A",$G63-$D63) -> 0.21 | I63: =$B63-$E63 -> 0 | J63: =$F63-$C63 -> 525 | K63: =IF($E63=0,"—",IF($G63>=Comm_Slab2_Start,"0.0325% of sell value","0.0175 paisa per share")) -> 0.0325% of sell value | L63: =IF($E63=0,0,IF($G63>=Comm_Slab2_Start,$F63*Comm_Slab2_Rate,$E63*Comm_Slab1_Paisa/Paisa_Per_PKR)) -> 175.25625 | M63: =$L63*SST_Rate -> 22.783313 | N63: =$L63+$M63 -> 198.03956 | O63: =$J63-$N63 -> 326.96044 | P63: =IF($C63=0,"N/A",$O63/$C63) -> 0.00060691529
A64: NRL-AUG | B64: 5000 | C64: 2446110 | D64: =IF($B64=0,"",$C64/$B64) -> 489.222 | E64: 5000 | F64: 2452650 | G64: =IF($E64=0,"",$F64/$E64) -> 490.53 | H64: =IF(OR($B64=0,$E64=0),"N/A",$G64-$D64) -> 1.308 | I64: =$B64-$E64 -> 0 | J64: =$F64-$C64 -> 6540 | K64: =IF($E64=0,"—",IF($G64>=Comm_Slab2_Start,"0.0325% of sell value","0.0175 paisa per share")) -> 0.0325% of sell value | L64: =IF($E64=0,0,IF($G64>=Comm_Slab2_Start,$F64*Comm_Slab2_Rate,$E64*Comm_Slab1_Paisa/Paisa_Per_PKR)) -> 797.11125 | M64: =$L64*SST_Rate -> 103.62446 | N64: =$L64+$M64 -> 900.73571 | O64: =$J64-$N64 -> 5639.2643 | P64: =IF($C64=0,"N/A",$O64/$C64) -> 0.0023054009
A65: OGDC-AUG | B65: 2500 | C65: 800370 | D65: =IF($B65=0,"",$C65/$B65) -> 320.148 | E65: 2500 | F65: 800250 | G65: =IF($E65=0,"",$F65/$E65) -> 320.1 | H65: =IF(OR($B65=0,$E65=0),"N/A",$G65-$D65) -> -0.048 | I65: =$B65-$E65 -> 0 | J65: =$F65-$C65 -> -120 | K65: =IF($E65=0,"—",IF($G65>=Comm_Slab2_Start,"0.0325% of sell value","0.0175 paisa per share")) -> 0.0325% of sell value | L65: =IF($E65=0,0,IF($G65>=Comm_Slab2_Start,$F65*Comm_Slab2_Rate,$E65*Comm_Slab1_Paisa/Paisa_Per_PKR)) -> 260.08125 | M65: =$L65*SST_Rate -> 33.810563 | N65: =$L65+$M65 -> 293.89181 | O65: =$J65-$N65 -> -413.89181 | P65: =IF($C65=0,"N/A",$O65/$C65) -> -0.0005171256
A66: PPL-AUG | B66: 5000 | C66: 1199450 | D66: =IF($B66=0,"",$C66/$B66) -> 239.89 | E66: 5000 | F66: 1207500 | G66: =IF($E66=0,"",$F66/$E66) -> 241.5 | H66: =IF(OR($B66=0,$E66=0),"N/A",$G66-$D66) -> 1.61 | I66: =$B66-$E66 -> 0 | J66: =$F66-$C66 -> 8050 | K66: =IF($E66=0,"—",IF($G66>=Comm_Slab2_Start,"0.0325% of sell value","0.0175 paisa per share")) -> 0.0325% of sell value | L66: =IF($E66=0,0,IF($G66>=Comm_Slab2_Start,$F66*Comm_Slab2_Rate,$E66*Comm_Slab1_Paisa/Paisa_Per_PKR)) -> 392.4375 | M66: =$L66*SST_Rate -> 51.016875 | N66: =$L66+$M66 -> 443.45438 | O66: =$J66-$N66 -> 7606.5456 | P66: =IF($C66=0,"N/A",$O66/$C66) -> 0.0063416946
A67: PRL-AUG | B67: 71000 | C67: 5869290 | D67: =IF($B67=0,"",$C67/$B67) -> 82.666056 | E67: 71000 | F67: 5876320 | G67: =IF($E67=0,"",$F67/$E67) -> 82.76507 | H67: =IF(OR($B67=0,$E67=0),"N/A",$G67-$D67) -> 0.099014085 | I67: =$B67-$E67 -> 0 | J67: =$F67-$C67 -> 7030 | K67: =IF($E67=0,"—",IF($G67>=Comm_Slab2_Start,"0.0325% of sell value","0.0175 paisa per share")) -> 0.0325% of sell value | L67: =IF($E67=0,0,IF($G67>=Comm_Slab2_Start,$F67*Comm_Slab2_Rate,$E67*Comm_Slab1_Paisa/Paisa_Per_PKR)) -> 1909.804 | M67: =$L67*SST_Rate -> 248.27452 | N67: =$L67+$M67 -> 2158.0785 | O67: =$J67-$N67 -> 4871.9215 | P67: =IF($C67=0,"N/A",$O67/$C67) -> 0.00083006999
A68: PSO-AUG | B68: 2500 | C68: 969500 | D68: =IF($B68=0,"",$C68/$B68) -> 387.8 | E68: 2500 | F68: 970000 | G68: =IF($E68=0,"",$F68/$E68) -> 388 | H68: =IF(OR($B68=0,$E68=0),"N/A",$G68-$D68) -> 0.2 | I68: =$B68-$E68 -> 0 | J68: =$F68-$C68 -> 500 | K68: =IF($E68=0,"—",IF($G68>=Comm_Slab2_Start,"0.0325% of sell value","0.0175 paisa per share")) -> 0.0325% of sell value | L68: =IF($E68=0,0,IF($G68>=Comm_Slab2_Start,$F68*Comm_Slab2_Rate,$E68*Comm_Slab1_Paisa/Paisa_Per_PKR)) -> 315.25 | M68: =$L68*SST_Rate -> 40.9825 | N68: =$L68+$M68 -> 356.2325 | O68: =$J68-$N68 -> 143.7675 | P68: =IF($C68=0,"N/A",$O68/$C68) -> 0.00014829036
A69: SSGC-AUG | B69: 7500 | C69: 216300 | D69: =IF($B69=0,"",$C69/$B69) -> 28.84 | E69: 7500 | F69: 216750 | G69: =IF($E69=0,"",$F69/$E69) -> 28.9 | H69: =IF(OR($B69=0,$E69=0),"N/A",$G69-$D69) -> 0.06 | I69: =$B69-$E69 -> 0 | J69: =$F69-$C69 -> 450 | K69: =IF($E69=0,"—",IF($G69>=Comm_Slab2_Start,"0.0325% of sell value","0.0175 paisa per share")) -> 0.0175 paisa per share | L69: =IF($E69=0,0,IF($G69>=Comm_Slab2_Start,$F69*Comm_Slab2_Rate,$E69*Comm_Slab1_Paisa/Paisa_Per_PKR)) -> 1.3125 | M69: =$L69*SST_Rate -> 0.170625 | N69: =$L69+$M69 -> 1.483125 | O69: =$J69-$N69 -> 448.51688 | P69: =IF($C69=0,"N/A",$O69/$C69) -> 0.002073587
A70: TOTAL | B70: =SUM(B63:B69) -> 96000 | C70: =SUM(C63:C69) -> 12039745 | D70: =IF($B70=0,"",$C70/$B70) -> 125.41401 | E70: =SUM(E63:E69) -> 96000 | F70: =SUM(F63:F69) -> 12062720 | G70: =IF($E70=0,"",$F70/$E70) -> 125.65333 | H70: =IF(OR($B70=0,$E70=0),"N/A",$G70-$D70) -> 0.23932292 | I70: =$B70-$E70 -> 0 | J70: =SUM(J63:J69) -> 22975 | L70: =SUM(L63:L69) -> 3851.2528 | M70: =SUM(M63:M69) -> 500.66286 | N70: =$L70+$M70 -> 4351.9156 | O70: =SUM(O63:O69) -> 18623.084 | P70: =IF($C70=0,"N/A",$O70/$C70) -> 0.0015468006
A73: Daily Trade Summary — 20 Aug 2026
A74: Gross intraday buy/sell flow • commission & SST • net P&L (all values PKR) | D74: Day Results
A75: Trading Date: | B75: 46254 | D75: Total Buy Value | E75: =C94 -> 10062968
A76: Account: | B76: THM00601 (A/c 91404) | D76: Total Sell Value | E76: =F94 -> 10084865
A77: Market: | B77: FUT (futures/derivatives), Reg (regular/cash market) | D77: Gross P&L | E77: =J94 -> 21896.51
A78: Trading Session: | B78: Full day 00:00–23:59 (per source log) | D78: Commission | E78: =L94 -> 3277.581
A79: Currency: | B79: PKR | D79: SST (13%) | E79: =M94 -> 426.08553
A80: Source File: | B80: TradeLog-20-08-2026.txt | D80: Total Charges | E80: =N94 -> 3703.6665
D81: Net P&L | E81: =O94 -> 18192.844
D82: Return on Buy | E82: =P94 -> 0.0018079004
D83: Net Position (shares) | E83: =I94 -> 0
A84: Symbol-Level Summary
A85: Symbol | B85: Buy Qty | C85: Buy Value (PKR) | D85: Avg Buy Price | E85: Sell Qty | F85: Sell Value (PKR) | G85: Avg Sell Price | H85: Price Diff (Sell−Buy) | I85: Net Qty | J85: Gross P&L (PKR) | K85: Commission Rate (Slab) | L85: Commission (PKR) | M85: SST 13% (PKR) | N85: Total Charges (PKR) | O85: Net P&L (PKR) | P85: Return on Buy
A86: NRL | B86: 1000 | C86: 487753 | D86: =IF($B86=0,"",$C86/$B86) -> 487.753 | E86: 1000 | F86: 490750 | G86: =IF($E86=0,"",$F86/$E86) -> 490.75 | H86: =IF(OR($B86=0,$E86=0),"N/A",$G86-$D86) -> 2.997 | I86: =$B86-$E86 -> 0 | J86: =$F86-$C86 -> 2997 | K86: =IF($E86=0,"—",IF($G86>=Comm_Slab2_Start,"0.0325% of sell value","0.0175 paisa per share")) -> 0.0325% of sell value | L86: =IF($E86=0,0,IF($G86>=Comm_Slab2_Start,$F86*Comm_Slab2_Rate,$E86*Comm_Slab1_Paisa/Paisa_Per_PKR)) -> 159.49375 | M86: =$L86*SST_Rate -> 20.734188 | N86: =$L86+$M86 -> 180.22794 | O86: =$J86-$N86 -> 2816.7721 | P86: =IF($C86=0,"N/A",$O86/$C86) -> 0.0057749969
A87: NRL-AUG | B87: 1000 | C87: 493500 | D87: =IF($B87=0,"",$C87/$B87) -> 493.5 | E87: 1000 | F87: 494800 | G87: =IF($E87=0,"",$F87/$E87) -> 494.8 | H87: =IF(OR($B87=0,$E87=0),"N/A",$G87-$D87) -> 1.3 | I87: =$B87-$E87 -> 0 | J87: =$F87-$C87 -> 1300 | K87: =IF($E87=0,"—",IF($G87>=Comm_Slab2_Start,"0.0325% of sell value","0.0175 paisa per share")) -> 0.0325% of sell value | L87: =IF($E87=0,0,IF($G87>=Comm_Slab2_Start,$F87*Comm_Slab2_Rate,$E87*Comm_Slab1_Paisa/Paisa_Per_PKR)) -> 160.81 | M87: =$L87*SST_Rate -> 20.9053 | N87: =$L87+$M87 -> 181.7153 | O87: =$J87-$N87 -> 1118.2847 | P87: =IF($C87=0,"N/A",$O87/$C87) -> 0.0022660278
A88: OGDC | B88: 500 | C88: 159850 | D88: =IF($B88=0,"",$C88/$B88) -> 319.7 | E88: 500 | F88: 159975 | G88: =IF($E88=0,"",$F88/$E88) -> 319.95 | H88: =IF(OR($B88=0,$E88=0),"N/A",$G88-$D88) -> 0.25 | I88: =$B88-$E88 -> 0 | J88: =$F88-$C88 -> 125 | K88: =IF($E88=0,"—",IF($G88>=Comm_Slab2_Start,"0.0325% of sell value","0.0175 paisa per share")) -> 0.0325% of sell value | L88: =IF($E88=0,0,IF($G88>=Comm_Slab2_Start,$F88*Comm_Slab2_Rate,$E88*Comm_Slab1_Paisa/Paisa_Per_PKR)) -> 51.991875 | M88: =$L88*SST_Rate -> 6.7589438 | N88: =$L88+$M88 -> 58.750819 | O88: =$J88-$N88 -> 66.249181 | P88: =IF($C88=0,"N/A",$O88/$C88) -> 0.00041444593
A89: OGDC-AUG | B89: 10000 | C89: 3210950 | D89: =IF($B89=0,"",$C89/$B89) -> 321.095 | E89: 10000 | F89: 3214600 | G89: =IF($E89=0,"",$F89/$E89) -> 321.46 | H89: =IF(OR($B89=0,$E89=0),"N/A",$G89-$D89) -> 0.365 | I89: =$B89-$E89 -> 0 | J89: =$F89-$C89 -> 3650 | K89: =IF($E89=0,"—",IF($G89>=Comm_Slab2_Start,"0.0325% of sell value","0.0175 paisa per share")) -> 0.0325% of sell value | L89: =IF($E89=0,0,IF($G89>=Comm_Slab2_Start,$F89*Comm_Slab2_Rate,$E89*Comm_Slab1_Paisa/Paisa_Per_PKR)) -> 1044.745 | M89: =$L89*SST_Rate -> 135.81685 | N89: =$L89+$M89 -> 1180.5619 | O89: =$J89-$N89 -> 2469.4381 | P89: =IF($C89=0,"N/A",$O89/$C89) -> 0.00076906777
A90: PPL-AUG | B90: 5000 | C90: 1192545 | D90: =IF($B90=0,"",$C90/$B90) -> 238.509 | E90: 5000 | F90: 1193550 | G90: =IF($E90=0,"",$F90/$E90) -> 238.71 | H90: =IF(OR($B90=0,$E90=0),"N/A",$G90-$D90) -> 0.201 | I90: =$B90-$E90 -> 0 | J90: =$F90-$C90 -> 1005 | K90: =IF($E90=0,"—",IF($G90>=Comm_Slab2_Start,"0.0325% of sell value","0.0175 paisa per share")) -> 0.0325% of sell value | L90: =IF($E90=0,0,IF($G90>=Comm_Slab2_Start,$F90*Comm_Slab2_Rate,$E90*Comm_Slab1_Paisa/Paisa_Per_PKR)) -> 387.90375 | M90: =$L90*SST_Rate -> 50.427487 | N90: =$L90+$M90 -> 438.33124 | O90: =$J90-$N90 -> 566.66876 | P90: =IF($C90=0,"N/A",$O90/$C90) -> 0.000475176
A91: PRL | B91: 10000 | C91: 827000 | D91: =IF($B91=0,"",$C91/$B91) -> 82.7 | E91: 10000 | F91: 829249.51 | G91: =IF($E91=0,"",$F91/$E91) -> 82.924951 | H91: =IF(OR($B91=0,$E91=0),"N/A",$G91-$D91) -> 0.224951 | I91: =$B91-$E91 -> 0 | J91: =$F91-$C91 -> 2249.51 | K91: =IF($E91=0,"—",IF($G91>=Comm_Slab2_Start,"0.0325% of sell value","0.0175 paisa per share")) -> 0.0325% of sell value | L91: =IF($E91=0,0,IF($G91>=Comm_Slab2_Start,$F91*Comm_Slab2_Rate,$E91*Comm_Slab1_Paisa/Paisa_Per_PKR)) -> 269.50609 | M91: =$L91*SST_Rate -> 35.035792 | N91: =$L91+$M91 -> 304.54188 | O91: =$J91-$N91 -> 1944.9681 | P91: =IF($C91=0,"N/A",$O91/$C91) -> 0.0023518357
A92: PRL-AUG | B92: 33500 | C92: 2752815 | D92: =IF($B92=0,"",$C92/$B92) -> 82.173582 | E92: 33500 | F92: 2761315 | G92: =IF($E92=0,"",$F92/$E92) -> 82.427313 | H92: =IF(OR($B92=0,$E92=0),"N/A",$G92-$D92) -> 0.25373134 | I92: =$B92-$E92 -> 0 | J92: =$F92-$C92 -> 8500 | K92: =IF($E92=0,"—",IF($G92>=Comm_Slab2_Start,"0.0325% of sell value","0.0175 paisa per share")) -> 0.0325% of sell value | L92: =IF($E92=0,0,IF($G92>=Comm_Slab2_Start,$F92*Comm_Slab2_Rate,$E92*Comm_Slab1_Paisa/Paisa_Per_PKR)) -> 897.42737 | M92: =$L92*SST_Rate -> 116.66556 | N92: =$L92+$M92 -> 1014.0929 | O92: =$J92-$N92 -> 7485.9071 | P92: =IF($C92=0,"N/A",$O92/$C92) -> 0.0027193644
A93: PSO-AUG | B93: 2500 | C93: 938555 | D93: =IF($B93=0,"",$C93/$B93) -> 375.422 | E93: 2500 | F93: 940625 | G93: =IF($E93=0,"",$F93/$E93) -> 376.25 | H93: =IF(OR($B93=0,$E93=0),"N/A",$G93-$D93) -> 0.828 | I93: =$B93-$E93 -> 0 | J93: =$F93-$C93 -> 2070 | K93: =IF($E93=0,"—",IF($G93>=Comm_Slab2_Start,"0.0325% of sell value","0.0175 paisa per share")) -> 0.0325% of sell value | L93: =IF($E93=0,0,IF($G93>=Comm_Slab2_Start,$F93*Comm_Slab2_Rate,$E93*Comm_Slab1_Paisa/Paisa_Per_PKR)) -> 305.70312 | M93: =$L93*SST_Rate -> 39.741406 | N93: =$L93+$M93 -> 345.44453 | O93: =$J93-$N93 -> 1724.5555 | P93: =IF($C93=0,"N/A",$O93/$C93) -> 0.0018374581
A94: TOTAL | B94: =SUM(B86:B93) -> 63500 | C94: =SUM(C86:C93) -> 10062968 | D94: =IF($B94=0,"",$C94/$B94) -> 158.47194 | E94: =SUM(E86:E93) -> 63500 | F94: =SUM(F86:F93) -> 10084865 | G94: =IF($E94=0,"",$F94/$E94) -> 158.81676 | H94: =IF(OR($B94=0,$E94=0),"N/A",$G94-$D94) -> 0.34482693 | I94: =$B94-$E94 -> 0 | J94: =SUM(J86:J93) -> 21896.51 | L94: =SUM(L86:L93) -> 3277.581 | M94: =SUM(M86:M93) -> 426.08553 | N94: =$L94+$M94 -> 3703.6665 | O94: =SUM(O86:O93) -> 18192.844 | P94: =IF($C94=0,"N/A",$O94/$C94) -> 0.0018079004
A97: Daily Trade Summary — 21 Aug 2026
A98: Gross intraday buy/sell flow • commission & SST • net P&L (all values PKR) | D98: Day Results
A99: Trading Date: | B99: 46255 | D99: Total Buy Value | E99: =C117 -> 8763520
A100: Account: | B100: THM00601 (A/c 91404) | D100: Total Sell Value | E100: =F117 -> 8772484.3
A101: Market: | B101: FUT (futures/derivatives), Reg (regular/cash market) | D101: Gross P&L | E101: =J117 -> 8964.29
A102: Trading Session: | B102: Full day 00:00–23:59 (per source log) | D102: Commission | E102: =L117 -> 2851.0574
A103: Currency: | B103: PKR | D103: SST (13%) | E103: =M117 -> 370.63746
A104: Source File: | B104: TradeLog-21-08-2026.txt | D104: Total Charges | E104: =N117 -> 3221.6948
D105: Net P&L | E105: =O117 -> 5742.5952
D106: Return on Buy | E106: =P117 -> 0.00065528408
D107: Net Position (shares) | E107: =I117 -> 0
A108: Symbol-Level Summary
...

Sheet Settings
A1: Settings & Assumptions
A2: All commission/tax formulas in this workbook reference these cells (defined names).
A4: Setting | B4: Value | C4: Notes
A5: Commission Slab 1 Upper Rate | B5: 53.99999 | C5: Sell rate 0.00000 – 53.99999 → Slab 1 (sell-side only)
A6: Commission Slab 1 Rate | B6: 0.0175 | C6: 0.0175 paisa per share → PKR = Sell Qty × 0.0175 / 100
A7: Commission Slab 2 Starting Rate | B7: 54 | C7: Sell rate ≥ 54.00000 → Slab 2
A8: Commission Slab 2 Rate | B8: 0.000325 | C8: 0.0325% of sell value (fraction = 0.000325)
A9: SST Rate | B9: 0.13 | C9: 13% of commission amount
A10: Paisa per PKR | B10: 100 | C10: 100 paisa = 1 PKR
A11: Currency | B11: PKR | C11: All monetary values in Pakistani Rupees
A12: Commission Side | B12: Sell | C12: Commission is charged on the SELL side only (Sell + Short Sell)
A15: Methodology & Rules
A16: 1. Trade types: Buy = BUY. Sell = SELL. Short Sell = SELL (gross buy/sell flow treatment).
A17: 2. Gross P&L = Sell Value − Buy Value (intraday buy/sell FLOW calculation — not FIFO/average-cost accounting).
A18: 3. Avg Buy / Avg Sell prices are quantity-weighted: Total Value ÷ Total Quantity (never a simple average).
A19: 4. Commission, sell side only. The slab is selected by the sell rate; at symbol-summary level the
A20: quantity-weighted average sell rate of the symbol-day decides the slab for that whole day
A21: (if a day's fills straddle the 54 boundary, the weighted-average rate decides).
A22: 5. Slab 1 commission = Sell Qty × 0.0175 paisa / 100 (0.000175 PKR/share). Slab 2 = Sell Value × 0.0325%.
A23: 6. SST = 13% × Commission. Total Charges = Commission + SST. Net P&L = Gross P&L − Total Charges.
A24: 7. Return on Buy = Net P&L ÷ Buy Value. Period returns are recomputed from period totals (never averaged).
A25: 8. Executions are deduplicated by Trading Date + Execution ID before summarization (re-uploads change nothing).
A26: 9. One combined 'Daily Trade Summary' sheet holds one block per trading date, newest appended below.
... A28: segregated by account number before import; executions from other accounts never enter this workbook.
